Workbook
Name LastCol: COUNTA('2025'!$7:$7)+1
Name LastCol: COUNTA('2026'!$7:$7)+1
Name LastCol: COUNTA('New Sheet'!$7:$7)+1
Name LastCol: COUNTA(#REF!)+1
Name PrintArea_SET: OFFSET('2025'!#REF!,,,MATCH(REPT("z",255),'2025'!$A:$A),'2025'!LastCol)
Name PrintArea_SET: OFFSET('2026'!#REF!,,,MATCH(REPT("z",255),'2026'!$A:$A),'2026'!LastCol)
Name PrintArea_SET: OFFSET('New Sheet'!#REF!,,,MATCH(REPT("z",255),'New Sheet'!$A:$A),'New Sheet'!LastCol)
Name PrintArea_SET: OFFSET(#REF!,,,MATCH(REPT("z",255),#REF!),LastCol)
Name Savings: [1]Data!$E$3

Sheet Sheet2
A3: Count of JAN | B3: Column Labels
A4: Row Labels | B4: 0 | C4: 42 | D4: 155 | E4: 1079 | F4: 1381 | G4: 2733 | H4: 3092 | I4: Grand Total
A5: Angel One
A6: Coin by Zerodha MF
A7: Coin DCX
A8: Coinbase
A9: Fidelity
A10: Grow
A11: Robinhood
A12: Wazirx
A13: Zerodha
A14: Grand Total

Sheet Loan Payments
A1: Loan Payments | B1: Pending | C1: Total | D1: Cleared | E1: Interest | F1: EMI | H1: Pending | I1: Total
A2: Home Loan | B2: 19932.95 | C2: 22100.72 | D2: =C2-B2 -> 2167.77 | E2: 0.096 | F2: 23000 | H2: 21237.06 | I2: 21237.06
A3: Education Loan | B3: =9920.79 -> 9920.79 | C3: 9920.79 | D3: =C3-B3 -> 0 | E3: 0.0965 | F3: 12675 | H3: 9220.79 | I3: 9220.79
A4: Gold Loan | B4: 31599.82 | C4: 31599.82 | D4: =C4-B4 -> 0 | E4: 0.09 | H4: 16184.06 | I4: 16184.06
A5: Personal Loan | B5: 1791.44 | C5: =11000+4215.16 -> 15215.16 | D5: =C5-B5 -> 13423.72 | E5: 0.121 | F5: 0 | H5: 5065.96 | I5: 9943.62
A6: US Credit Cards | B6: =tblEntertainment3244[[#Totals],[Balance]] -> 2014 | C6: =6000 + 2200 -> 8200 | D6: =C6-B6 -> 6186 | E6: 0 | H6: =tblEntertainment3244[[#Totals],[Balance]] -> 2014 | I6: =tblEntertainment3244[[#Totals],[Balance]] -> 2014
A7: Car Loan | B7: 0 | C7: 5687.02 | D7: =C7-B7 -> 5687.02 | E7: 8
A8: Bike Loan | B8: 0 | C8: 1844.07 | D8: =C8-B8 -> 1844.07 | E8: 8
A9: My HDFC Personal Loan | B9: 0 | C9: 100 | D9: =C9-B9 -> 100
A10: Total | B10: =SUM(B2:B9) -> 65259 | C10: =SUM(C2:C6) -> 87036.49 | D10: =C10-B10 -> 21777.49 | H10: =SUM(H2:H6) -> 53721.87 | I10: =SUM(I2:I6) -> 58599.53

Sheet 2026
A5: =tblRecreation3546[[#Totals],[Invested Total]] -> 18757.47 | G5: =P107 -> 65259
A7: REVENUE
A8: INCOME | B8: JAN | C8: FEB | D8: MAR | E8: APR | F8: MAY | G8: JUN | H8: JUL | I8: AUG | J8: SEP | K8: OCT | L8: NOV | M8: DEC | N8: YEAR | O8: Last Updated on | P8: Column1
A9: Wages Week 1 | C9: 2729.16 | D9: 40 | E9: 3016.99 | F9: 3016.99 | G9: =30.16+2986.83 -> 3016.99 | H9: =3020.05 + 30.5 -> 3050.55 | N9: =SUM(tblIncome2833[[#This Row],[JAN]:[DEC]]) -> 14870.68 | O9: 46224
A10: Wages Week 2 | C10: 3007 | D10: 3007 | E10: 3016.99 | F10: =2986.83+30.16 -> 3016.99 | G10: =2986.83+30.16 -> 3016.99 | H10: =3020.05 + 30.5 -> 3050.55 | N10: =SUM(tblIncome2833[[#This Row],[JAN]:[DEC]]) -> 18115.52
A11: Wages Week (Kooli Pani, PhoneBill reimbursment) | B11: 1600 | G11: 240 | N11: =SUM(tblIncome2833[[#This Row],[JAN]:[DEC]]) -> 1840
A12: Wages Week (taxes, HSA money) | C12: =1030 + 4185 -> 5215 | D12: 30 | E12: =94.39+75 -> 169.39 | F12: =70.31+9.97+29.73 -> 110.01 | N12: =SUM(tblIncome2833[[#This Row],[JAN]:[DEC]]) -> 5524.4
A13: Total | B13: =SUBTOTAL(109,tblIncome2833[JAN]) -> 1600 | C13: =SUBTOTAL(109,tblIncome2833[FEB]) -> 10951.16 | D13: =SUBTOTAL(109,tblIncome2833[MAR]) -> 3077 | E13: =SUBTOTAL(109,tblIncome2833[APR]) -> 6203.37 | F13: =SUBTOTAL(109,tblIncome2833[MAY]) -> 6143.99 | G13: =SUBTOTAL(109,tblIncome2833[JUN]) -> 6273.98 | H13: =SUBTOTAL(109,tblIncome2833[JUL]) -> 6101.1 | I13: =SUBTOTAL(109,tblIncome2833[AUG]) -> 0 | J13: =SUBTOTAL(109,tblIncome2833[SEP]) -> 0 | K13: =SUBTOTAL(109,tblIncome2833[OCT]) -> 0 | L13: =SUBTOTAL(109,tblIncome2833[NOV]) -> 0 | M13: =SUBTOTAL(109,tblIncome2833[DEC]) -> 0 | N13: =SUBTOTAL(109,tblIncome2833[YEAR]) -> 40350.6
A15: EXPENSES
A16: HOME | B16: JAN | C16: FEB | D16: MAR | E16: APR | F16: MAY | G16: JUN | H16: JUL | I16: AUG | J16: SEP | K16: OCT | L16: NOV | M16: DEC | N16: YEAR | O16: Last Updated on
A17: Mortgage | B17: 850 | C17: 800 | D17: 800 | E17: 800 | F17: 800 | G17: 400 | N17: =SUM(tblHome2941[[#This Row],[JAN]:[DEC]]) -> 4450 | O17: 46224
A18: Insurance | N18: =SUM(tblHome2941[[#This Row],[JAN]:[DEC]]) -> 0
A19: Deposit | D19: 800 | N19: =SUM(tblHome2941[[#This Row],[JAN]:[DEC]]) -> 800
A20: Utilities | B20: 109 | D20: 94.38 | E20: 59.1 | F20: 59.86 | G20: 59.67 | H20: 37.43 | N20: =SUM(tblHome2941[[#This Row],[JAN]:[DEC]]) -> 419.44
A21: College Expenses(Car + Gas + cofee + flights) | D21: =24.09+7.3+2+23.31+0.1+22.84+26.86+307.23+25+22.02+16.35+15.52+9.03 -> 501.65 | F21: =594.66+51+2.83+10.65+8.31+7.94+2.83+9.88 -> 688.1 | G21: 293.3 | N21: =SUM(tblHome2941[[#This Row],[JAN]:[DEC]]) -> 1483.05
A22: Total | B22: =SUBTOTAL(109,tblHome2941[JAN]) -> 959 | C22: =SUBTOTAL(109,tblHome2941[FEB]) -> 800 | D22: =SUBTOTAL(109,tblHome2941[MAR]) -> 2196.03 | E22: =SUBTOTAL(109,tblHome2941[APR]) -> 859.1 | F22: =SUBTOTAL(109,tblHome2941[MAY]) -> 1547.96 | G22: =SUBTOTAL(109,tblHome2941[JUN]) -> 752.97 | H22: =SUBTOTAL(109,tblHome2941[JUL]) -> 37.43 | I22: =SUBTOTAL(109,tblHome2941[AUG]) -> 0 | J22: =SUBTOTAL(109,tblHome2941[SEP]) -> 0 | K22: =SUBTOTAL(109,tblHome2941[OCT]) -> 0 | L22: =SUBTOTAL(109,tblHome2941[NOV]) -> 0 | M22: =SUBTOTAL(109,tblHome2941[DEC]) -> 0 | N22: =SUBTOTAL(109,tblHome2941[YEAR]) -> 7152.49
A24: DAILY LIVING | B24: JAN | C24: FEB | D24: MAR | E24: APR | F24: MAY | G24: JUN | H24: JUL | I24: AUG | J24: SEP | K24: OCT | L24: NOV | M24: DEC | N24: YEAR | O24: Last Updated on
A25: Split Wise | B25: 90 | C25: 270 | N25: =SUM(tblDaily3042[[#This Row],[JAN]:[DEC]]) -> 360 | O25: 46224
A26: Groceries(Indian) | B26: 308 | C26: 244 | D26: 27.64 | E26: 58.3 | F26: 20 | G26: =9.62+29.96 -> 39.58 | N26: =SUM(tblDaily3042[[#This Row],[JAN]:[DEC]]) -> 697.52
A27: Shifting to new places | C27: 85 | N27: =SUM(tblDaily3042[[#This Row],[JAN]:[DEC]]) -> 85
A28: Walmart | D28: =31.62+10.01+15.38+2.61+39.43 -> 99.05 | E28: =45.3+6.16+48.47+25.62+19.47+14.71+37.19 -> 196.92 | F28: =-8.41+40.31+38.67+44.49+27.12+2 -> 144.18 | G28: =19.97+9.94+21.51+2.42+10.06+5.23+34+33+8.94-26 -> 119.07 | H28: =13+8.25+39.48 -> 60.73 | N28: =SUM(tblDaily3042[[#This Row],[JAN]:[DEC]]) -> 619.95
A29: Dining out | C29: 1.87 | D29: =6+16.04+1+11 -> 34.04 | E29: =3.1+17.16+23.75+5.76+1.56+5.3+15.85 -> 72.48 | F29: =7.7+6.92+9.07 -> 23.69 | G29: =2+4.06+12+5.62+1.06+7+3+4.54+1 -> 40.28 | H29: 9.24 | N29: =SUM(tblDaily3042[[#This Row],[JAN]:[DEC]]) -> 181.6
A30: Other home expenses (Amazon, dollar tree, costco) | B30: 96.25 | C30: 64 | D30: =10.62+2.61 -> 13.23 | E30: 58.96 | G30: 63.71 | N30: =SUM(tblDaily3042[[#This Row],[JAN]:[DEC]]) -> 296.15
A31: Fun Activities(Board Games, Outdoor Activities) | F31: 7.28 | G31: =12.49+11.65+ 13 -> 37.14 | N31: =SUM(tblDaily3042[[#This Row],[JAN]:[DEC]]) -> 44.42
A32: Total | B32: =SUBTOTAL(109,tblDaily3042[JAN]) -> 494.25 | C32: =SUBTOTAL(109,tblDaily3042[FEB]) -> 664.87 | D32: =SUBTOTAL(109,tblDaily3042[MAR]) -> 173.96 | E32: =SUBTOTAL(109,tblDaily3042[APR]) -> 386.66 | F32: =SUBTOTAL(109,tblDaily3042[MAY]) -> 195.15 | G32: =SUBTOTAL(109,tblDaily3042[JUN]) -> 299.78 | H32: =SUBTOTAL(109,tblDaily3042[JUL]) -> 69.97 | I32: =SUBTOTAL(109,tblDaily3042[AUG]) -> 0 | J32: =SUBTOTAL(109,tblDaily3042[SEP]) -> 0 | K32: =SUBTOTAL(109,tblDaily3042[OCT]) -> 0 | L32: =SUBTOTAL(109,tblDaily3042[NOV]) -> 0 | M32: =SUBTOTAL(109,tblDaily3042[DEC]) -> 0 | N32: =SUBTOTAL(109,tblDaily3042[YEAR]) -> 2284.64
A34: TRANSPORTATION | B34: JAN | C34: FEB | D34: MAR | E34: APR | F34: MAY | G34: JUN | H34: JUL | I34: AUG | J34: SEP | K34: OCT | L34: NOV | M34: DEC | N34: YEAR | O34: Last Updated on
A35: Public transportation | B35: 4 | C35: 50.84 | D35: =7.5+7.5+7.5 -> 22.5 | E35: =2.57+2.5+2.57+2.57 -> 10.21 | F35: 11.32 | G35: 2.32 | H35: =8.23+3.09+7.72+5 -> 24.04 | N35: =SUM(tblTransportation3143[[#This Row],[JAN]:[DEC]]) -> 125.23 | O35: 46224
A36: Friends transportation | C36: 8.5 | D36: 2.25 | N36: =SUM(tblTransportation3143[[#This Row],[JAN]:[DEC]]) -> 10.75
A37: Cabs | C37: 5.34 | N37: =SUM(tblTransportation3143[[#This Row],[JAN]:[DEC]]) -> 5.34
A38: Total | B38: =SUBTOTAL(109,tblTransportation3143[JAN]) -> 4 | C38: =SUBTOTAL(109,tblTransportation3143[FEB]) -> 64.68 | D38: =SUBTOTAL(109,tblTransportation3143[MAR]) -> 24.75 | E38: =SUBTOTAL(109,tblTransportation3143[APR]) -> 10.21 | F38: =SUBTOTAL(109,tblTransportation3143[MAY]) -> 11.32 | G38: =SUBTOTAL(109,tblTransportation3143[JUN]) -> 2.32 | H38: =SUBTOTAL(109,tblTransportation3143[JUL]) -> 24.04 | I38: =SUBTOTAL(109,tblTransportation3143[AUG]) -> 0 | J38: =SUBTOTAL(109,tblTransportation3143[SEP]) -> 0 | K38: =SUBTOTAL(109,tblTransportation3143[OCT]) -> 0 | L38: =SUBTOTAL(109,tblTransportation3143[NOV]) -> 0 | M38: =SUBTOTAL(109,tblTransportation3143[DEC]) -> 0 | N38: =SUBTOTAL(109,tblTransportation3143[YEAR]) -> 141.32
A40: Credit Card | B40: JAN | C40: FEB | D40: MAR | E40: APR | F40: MAY | G40: JUN | H40: JUL | I40: AUG | J40: SEP | K40: OCT | L40: NOV | M40: DEC | N40: YEAR | O40: Last Updated on | P40: Balance
A41: Chase | B41: 48 | C41: 252 | D41: 300 | E41: 100 | N41: =SUM(tblEntertainment3244[[#This Row],[JAN]:[DEC]]) -> 700 | O41: 46224 | P41: 1000
A42: Amex(fee) | B42: 8.95 | G42: 325 | N42: =SUM(tblEntertainment3244[[#This Row],[JAN]:[DEC]]) -> 333.95 | P42: 0
A43: Capital One | N43: =SUM(tblEntertainment3244[[#This Row],[JAN]:[DEC]]) -> 0 | P43: 0
A44: Discover | C44: 176.62 | D44: 200 | E44: 100 | N44: =SUM(tblEntertainment3244[[#This Row],[JAN]:[DEC]]) -> 476.62 | P44: 1014
A45: Citi | N45: =SUM(tblEntertainment3244[[#This Row],[JAN]:[DEC]]) -> 0 | P45: 0
A46: BOFA | N46: =SUM(tblEntertainment3244[[#This Row],[JAN]:[DEC]]) -> 0
A47: Total | B47: =SUBTOTAL(109,tblEntertainment3244[JAN]) -> 56.95 | C47: =SUBTOTAL(109,tblEntertainment3244[FEB]) -> 428.62 | D47: =SUBTOTAL(109,tblEntertainment3244[MAR]) -> 500 | E47: =SUBTOTAL(109,tblEntertainment3244[APR]) -> 200 | F47: =SUBTOTAL(109,tblEntertainment3244[MAY]) -> 0 | G47: =SUBTOTAL(109,tblEntertainment3244[JUN]) -> 325 | H47: =SUBTOTAL(109,tblEntertainment3244[JUL]) -> 0 | I47: =SUBTOTAL(109,tblEntertainment3244[AUG]) -> 0 | J47: =SUBTOTAL(109,tblEntertainment3244[SEP]) -> 0 | K47: =SUBTOTAL(109,tblEntertainment3244[OCT]) -> 0 | L47: =SUBTOTAL(109,tblEntertainment3244[NOV]) -> 0 | M47: =SUBTOTAL(109,tblEntertainment3244[DEC]) -> 0 | N47: =SUBTOTAL(109,tblEntertainment3244[YEAR]) -> 1510.57 | P47: =SUM(tblEntertainment3244[Balance]) -> 2014
A49: VACATIONS | B49: JAN | C49: FEB | D49: MAR | E49: APR | F49: MAY | G49: JUN | H49: JUL | I49: AUG | J49: SEP | K49: OCT | L49: NOV | M49: DEC | N49: YEAR | O49: Last Updated on
A50: Trips | C50: 519 | E50: =22.5+18.5 -> 41 | G50: =386.67+30.04 -> 416.71 | H50: =11.57+4.27+4+18.52+24.32+14.43+15.92+4.42+5.6+54.65+31.99+27.45+28.63+15+7.73+12.22+8.28+18.58 -> 307.58 | N50: =SUM(tblVacations3445[[#This Row],[JAN]:[DEC]]) -> 1284.29
A51: Accommodations | C51: 67 | N51: =SUM(tblVacations3445[[#This Row],[JAN]:[DEC]]) -> 67 | O51: 46224
A52: Movies | D52: =12.84+10.53 -> 23.37 | G52: 10 | N52: =SUM(tblVacations3445[[#This Row],[JAN]:[DEC]]) -> 33.37
A53: Airlines | B53: 421 | N53: =SUM(tblVacations3445[[#This Row],[JAN]:[DEC]]) -> 421
A54: Rental car | N54: =SUM(tblVacations3445[[#This Row],[JAN]:[DEC]]) -> 0
A55: Total | B55: =SUBTOTAL(109,tblVacations3445[JAN]) -> 421 | C55: =SUBTOTAL(109,tblVacations3445[FEB]) -> 586 | D55: =SUBTOTAL(109,tblVacations3445[MAR]) -> 23.37 | E55: =SUBTOTAL(109,tblVacations3445[APR]) -> 41 | F55: =SUBTOTAL(109,tblVacations3445[MAY]) -> 0 | G55: =SUBTOTAL(109,tblVacations3445[JUN]) -> 426.71 | H55: =SUBTOTAL(109,tblVacations3445[JUL]) -> 307.58 | I55: =SUM(tblVacations3445[AUG]) -> 0 | J55: =SUBTOTAL(109,tblVacations3445[SEP]) -> 0 | K55: =SUBTOTAL(109,tblVacations3445[OCT]) -> 0 | L55: =SUBTOTAL(109,tblVacations3445[NOV]) -> 0 | M55: =SUBTOTAL(109,tblVacations3445[DEC]) -> 0 | N55: =SUBTOTAL(109,tblVacations3445[YEAR]) -> 1805.66
A57: Investment | B57: JAN | C57: FEB | D57: MAR | E57: APR | F57: MAY | G57: JUN | H57: JUL | I57: AUG | J57: SEP | K57: OCT | L57: NOV | M57: DEC | N57: Current Value | O57: Invested Total | P57: YEAR | Q57: Last Updated on | R57: Notes
A58: Loans Given | D58: 3000 | E58: 4000 | N58: 7000 | O58: =SUM(tblRecreation3546[[#This Row],[JAN]:[DEC]]) -> 7000 | P58: =SUM(tblRecreation3546[[#This Row],[JAN]:[DEC]]) -> 7000
A59: Robinhood | E59: 49.44 | F59: =15+15 -> 30 | G59: =15+15+15 -> 45 | H59: =15+15 -> 30 | N59: 2900 | O59: =2733+SUM(tblRecreation3546[[#This Row],[JAN]:[JUN]]) -> 2857.44 | P59: =SUM(tblRecreation3546[[#This Row],[JAN]:[DEC]]) -> 154.44 | Q59: 46224
A60: Coin by Zerodha MF | C60: 271.94 | D60: =905.41+106 -> 1011.41 | E60: =268.32+159.15 -> 427.47 | N60: 1802.31 | O60: =155 + SUM(tblRecreation3546[[#This Row],[JAN]:[JUN]]) -> 1865.82 | P60: =SUM(tblRecreation3546[[#This Row],[JAN]:[DEC]]) -> 1710.82
A61: Grow | E61: 159.15 | F61: 158.86 | N61: 1559.89 | O61: =1079+ SUM(tblRecreation3546[[#This Row],[JAN]:[JUN]]) -> 1397.01 | P61: =SUM(tblRecreation3546[[#This Row],[JAN]:[DEC]]) -> 318.01
A62: Fidelity | N62: 2082 | O62: =1381 +SUM(tblRecreation3546[[#This Row],[JAN]:[JUN]]) -> 1381 | P62: =SUM(tblRecreation3546[[#This Row],[JAN]:[DEC]]) -> 0
A63: Zerodha | D63: 433.08 | N63: 1391.26 | O63: 1374.02 | P63: =SUM(tblRecreation3546[[#This Row],[JAN]:[DEC]]) -> 433.08
A64: Angel Investing | E64: 1180 | H64: 529.81 | N64: 1180 | O64: =SUM(tblRecreation3546[[#This Row],[JAN]:[DEC]]) -> 1709.81 | P64: =SUM(tblRecreation3546[[#This Row],[JAN]:[DEC]]) -> 1709.81 | R64: My Pahadi Ducan, Babbai Tiffins, Whole Leaf Organics(for this whole leaf organics keerthana paid the full amount, I didn’t pay anything)
A65: Angel One | N65: 754.75 | O65: =1130.37+ SUM(tblRecreation3546[[#This Row],[JAN]:[JUN]]) -> 1130.37 | P65: =SUM(tblRecreation3546[[#This Row],[JAN]:[DEC]]) -> 0
A66: Coinbase | N66: 30 | O66: =42+SUM(tblRecreation3546[[#This Row],[JAN]:[JUN]]) -> 42 | P66: =SUM(tblRecreation3546[[#This Row],[JAN]:[DEC]]) -> 0
A67: Coin DCX | O67: =SUM(tblRecreation3546[[#This Row],[JAN]:[DEC]]) -> 0 | P67: =SUM(tblRecreation3546[[#This Row],[JAN]:[DEC]]) -> 0
A68: Total | B68: =SUBTOTAL(109,tblRecreation3546[JAN]) -> 0 | C68: =SUBTOTAL(109,tblRecreation3546[FEB]) -> 271.94 | D68: =SUBTOTAL(109,tblRecreation3546[MAR]) -> 4444.49 | E68: =SUBTOTAL(109,tblRecreation3546[APR]) -> 5816.06 | F68: =SUBTOTAL(109,tblRecreation3546[MAY]) -> 188.86 | G68: =SUBTOTAL(109,tblRecreation3546[JUN]) -> 45 | H68: =SUBTOTAL(109,tblRecreation3546[JUL]) -> 559.81 | I68: =SUBTOTAL(109,tblRecreation3546[AUG]) -> 0 | J68: =SUBTOTAL(109,tblRecreation3546[SEP]) -> 0 | K68: =SUBTOTAL(109,tblRecreation3546[OCT]) -> 0 | L68: =SUBTOTAL(109,tblRecreation3546[NOV]) -> 0 | M68: =SUBTOTAL(109,tblRecreation3546[DEC]) -> 0 | N68: =SUM(tblRecreation3546[Current Value]) -> 18700.21 | O68: =SUM(tblRecreation3546[Invested Total]) -> 18757.47 | P68: =SUBTOTAL(109,tblRecreation3546[YEAR]) -> 11326.16
A70: DUES/SUBSCRIPTION | B70: JAN | C70: FEB | D70: MAR | E70: APR | F70: MAY | G70: JUN | H70: JUL | I70: AUG | J70: SEP | K70: OCT | L70: NOV | M70: DEC | N70: YEAR | O70: Last Updated on
A71: Internet connection | B71: 51.54 | C71: 51.52 | D71: 51.51 | E71: 51.5 | F71: 56.54 | G71: 56.54 | N71: =SUM(tblDues3647[[#This Row],[JAN]:[DEC]]) -> 319.15 | O71: 46224
A72: Wifi | B72: 10 | N72: =SUM(tblDues3647[[#This Row],[JAN]:[DEC]]) -> 10
A73: Youtube | D73: 3.67 | E73: 3.83 | G73: 4.5 | N73: =SUM(tblDues3647[[#This Row],[JAN]:[DEC]]) -> 12
A74: Apple & Google One Subscriptions | B74: 2.99 | C74: 2.99 | D74: 2.99 | E74: 2.99 | F74: 2.99 | G74: 2.99 | N74: =SUM(tblDues3647[[#This Row],[JAN]:[DEC]]) -> 17.94
A75: Total | B75: =SUBTOTAL(109,tblDues3647[JAN]) -> 64.53 | C75: =SUBTOTAL(109,tblDues3647[FEB]) -> 54.51 | D75: =SUBTOTAL(109,tblDues3647[MAR]) -> 58.17 | E75: =SUBTOTAL(109,tblDues3647[APR]) -> 58.32 | F75: =SUBTOTAL(109,tblDues3647[MAY]) -> 59.53 | G75: =SUBTOTAL(109,tblDues3647[JUN]) -> 64.03 | H75: =SUBTOTAL(109,tblDues3647[JUL]) -> 0 | I75: =SUBTOTAL(109,tblDues3647[AUG]) -> 0 | J75: =SUBTOTAL(109,tblDues3647[SEP]) -> 0 | K75: =SUBTOTAL(109,tblDues3647[OCT]) -> 0 | L75: =SUBTOTAL(109,tblDues3647[NOV]) -> 0 | M75: =SUBTOTAL(109,tblDues3647[DEC]) -> 0 | N75: =SUBTOTAL(109,tblDues3647[YEAR]) -> 359.09
A77: PERSONAL | B77: JAN | C77: FEB | D77: MAR | E77: APR | F77: MAY | G77: JUN | H77: JUL | I77: AUG | J77: SEP | K77: OCT | L77: NOV | M77: DEC | N77: YEAR | O77: Last Updated on
A78: Self Learning(Open API) | F78: 26.55 | N78: =SUM(tblPersonal3748[[#This Row],[JAN]:[DEC]]) -> 26.55
A79: Clothing | C79: 5 | F79: 39.8 | G79: 85+10.60 | H79: 45 | N79: =SUM(tblPersonal3748[[#This Row],[JAN]:[DEC]]) -> 89.8 | O79: 46224
A80: Gifts | G80: 99.81 | H80: 21.1 | N80: =SUM(tblPersonal3748[[#This Row],[JAN]:[DEC]]) -> 120.91
A81: Salon/barber | B81: 11.99 | N81: =SUM(tblPersonal3748[[#This Row],[JAN]:[DEC]]) -> 11.99
A82: Self Care (sunscreen, moisturizer) | E82: =37.99+70.31 -> 108.3 | F82: =72.17+34.93 -> 107.1 | G82: 14.25 | N82: =SUM(tblPersonal3748[[#This Row],[JAN]:[DEC]]) -> 229.65
A83: Health Care(Checkups) | D83: 70 | N83: =SUM(tblPersonal3748[[#This Row],[JAN]:[DEC]]) -> 70
A84: Total | B84: =SUBTOTAL(109,tblPersonal3748[JAN]) -> 11.99 | C84: =SUBTOTAL(109,tblPersonal3748[FEB]) -> 5 | D84: =SUBTOTAL(109,tblPersonal3748[MAR]) -> 70 | E84: =SUBTOTAL(109,tblPersonal3748[APR]) -> 108.3 | F84: =SUBTOTAL(109,tblPersonal3748[MAY]) -> 173.45 | G84: =SUBTOTAL(109,tblPersonal3748[JUN]) -> 114.06 | H84: =SUBTOTAL(109,tblPersonal3748[JUL]) -> 66.1 | I84: =SUBTOTAL(109,tblPersonal3748[AUG]) -> 0 | J84: =SUBTOTAL(109,tblPersonal3748[SEP]) -> 0 | K84: =SUBTOTAL(109,tblPersonal3748[OCT]) -> 0 | L84: =SUBTOTAL(109,tblPersonal3748[NOV]) -> 0 | M84: =SUBTOTAL(109,tblPersonal3748[DEC]) -> 0 | N84: =SUBTOTAL(109,tblPersonal3748[YEAR]) -> 548.9
A86: FINANCIAL OBLIGATIONS | B86: JAN | C86: FEB | D86: MAR | E86: APR | F86: MAY | G86: JUN | H86: JUL | I86: AUG | J86: SEP | K86: OCT | L86: NOV | M86: DEC | N86: YEAR | O86: Last Updated on | P86: Column1
A87: Family Loan Sendings | B87: 1000 | C87: =1500 + 2990.99 -> 4490.99 | D87: =1500+500+1000+400+1300 -> 4700 | E87: =500+300+1000 -> 1800 | F87: =500+500+300+100 -> 1400 | G87: =1000+150+500 -> 1650 | H87: 221 | N87: =SUM(tblFinancial3849[[#This Row],[JAN]:[DEC]]) -> 15261.99 | O87: 46224
A88: Family expenses | D88: =1500+500+1000+400 -> 3400 | E88: =500+300+1000 -> 1800 | F88: =440+329 -> 769 | N88: =SUM(tblFinancial3849[[#This Row],[JAN]:[DEC]]) -> 5969
A89: Income tax (additional) | C89: 150 | N89: =SUM(tblFinancial3849[[#This Row],[JAN]:[DEC]]) -> 150
A90: Second Masters | B90: 43 | C90: 789.52 | D90: 766.52 | E90: 789.52 | F90: =440+329+800+100 -> 1669 | G90: =700+200+400+200+200 -> 1700 | H90: =400+70.99 -> 470.99 | N90: =SUM(tblFinancial3849[[#This Row],[JAN]:[DEC]]) -> 6228.55
A91: Other obligations (India ki family items) | G91: =31.38+70.15 -> 101.53 | N91: =SUM(tblFinancial3849[[#This Row],[JAN]:[DEC]]) -> 101.53
A92: Total | B92: =SUBTOTAL(109,tblFinancial3849[JAN]) -> 1043 | C92: =SUBTOTAL(109,tblFinancial3849[FEB]) -> 5430.51 | D92: =SUBTOTAL(109,tblFinancial3849[MAR]) -> 8866.52 | E92: =SUBTOTAL(109,tblFinancial3849[APR]) -> 4389.52 | F92: =SUBTOTAL(109,tblFinancial3849[MAY]) -> 3838 | G92: =SUBTOTAL(109,tblFinancial3849[JUN]) -> 3451.53 | H92: =SUBTOTAL(109,tblFinancial3849[JUL]) -> 691.99 | I92: =SUBTOTAL(109,tblFinancial3849[AUG]) -> 0 | J92: =SUBTOTAL(109,tblFinancial3849[SEP]) -> 0 | K92: =SUBTOTAL(109,tblFinancial3849[OCT]) -> 0 | L92: =SUBTOTAL(109,tblFinancial3849[NOV]) -> 0 | M92: =SUBTOTAL(109,tblFinancial3849[DEC]) -> 0 | N92: =SUBTOTAL(109,tblFinancial3849[YEAR]) -> 27711.07
A94: MISC PAYMENTS | B94: JAN | C94: FEB | D94: MAR | E94: APR | F94: MAY | G94: JUN | H94: JUL | I94: AUG | J94: SEP | K94: OCT | L94: NOV | M94: DEC | N94: YEAR | O94: Last Updated on
A95: Other(gambling, ups) | C95: 80 | E95: =43.93+30+10.62 -> 84.55 | N95: =SUM(tblMisc3950[[#This Row],[JAN]:[DEC]]) -> 164.55 | O95: 46224
A96: Total | B96: =SUBTOTAL(109,tblMisc3950[JAN]) -> 0 | C96: =SUBTOTAL(109,tblMisc3950[FEB]) -> 80 | D96: =SUBTOTAL(109,tblMisc3950[MAR]) -> 0 | E96: =SUBTOTAL(109,tblMisc3950[APR]) -> 84.55 | F96: =SUBTOTAL(109,tblMisc3950[MAY]) -> 0 | G96: =SUBTOTAL(109,tblMisc3950[JUN]) -> 0 | H96: =SUBTOTAL(109,tblMisc3950[JUL]) -> 0 | I96: =SUBTOTAL(109,tblMisc3950[AUG]) -> 0 | J96: =SUBTOTAL(109,tblMisc3950[SEP]) -> 0 | K96: =SUBTOTAL(109,tblMisc3950[OCT]) -> 0 | L96: =SUBTOTAL(109,tblMisc3950[NOV]) -> 0 | M96: =SUBTOTAL(109,tblMisc3950[DEC]) -> 0 | N96: =SUBTOTAL(109,tblMisc3950[YEAR]) -> 164.55
A98: Loan Payments | B98: JAN | C98: FEB | D98: MAR | E98: APR | F98: MAY | G98: JUN | H98: JUL | I98: AUG | J98: SEP | K98: OCT | L98: NOV | M98: DEC | N98: YEAR | O98: Last Updated on | P98: Pending | Q98: Total | R98: Cleared | S98: Interest | T98: EMI | W98: Pending | X98: Total
A99: Home Loan | N99: =SUM(B99:M99) -> 0 | O99: 46224 | P99: 19932.95 | Q99: 22100.72 | R99: =Q99-P99 -> 2167.77 | S99: 0.096 | T99: 23000 | W99: 21237.06 | X99: 21237.06
A100: Education Loan | N100: =SUM(B100:M100) -> 0 | P100: =9920.79 -> 9920.79 | Q100: 9920.79 | R100: =Q100-P100 -> 0 | S100: 0.0965 | T100: 12675 | W100: 9220.79 | X100: 9220.79
A101: Gold Loan | G101: 1000 | N101: =SUM(B101:M101) -> 1000 | P101: 31599.82 | Q101: 31599.82 | R101: =Q101-P101 -> 0 | S101: 0.09 | W101: 16184.06 | X101: 16184.06
A102: Personal Loan | N102: =SUM(B102:M102) -> 0 | P102: 1791.44 | Q102: =11000+4215.16 -> 15215.16 | R102: =Q102-P102 -> 13423.72 | S102: 0.121 | T102: 0 | W102: 5065.96 | X102: 9943.62
A103: US Credit Cards | H103: =1000+100+100+350+708.58+295+400+200 -> 3153.58 | N103: =SUM(B103:M103) -> 3153.58 | P103: =tblEntertainment3244[[#Totals],[Balance]] -> 2014 | Q103: =6000 + 2200 -> 8200 | R103: =Q103-P103 -> 6186 | S103: 0 | W103: =tblEntertainment3244[[#Totals],[Balance]] -> 2014 | X103: =tblEntertainment3244[[#Totals],[Balance]] -> 2014
A104: Car Loan | C104: 5000 | N104: =SUM(B104:M104) -> 5000 | P104: 0 | Q104: 5687.02 | R104: =Q104-P104 -> 5687.02 | S104: 8
A105: Bike Loan | N105: =SUM(B105:M105) -> 0 | P105: 0 | Q105: 1844.07 | R105: =Q105-P105 -> 1844.07 | S105: 8
A106: My HDFC Personal Loan | B106: 75 | C106: 75 | D106: 75 | E106: 75 | F106: 75 | G106: 75 | N106: =SUM(B106:M106) -> 450 | P106: 0 | Q106: 400 | R106: =Q106-P106 -> 400
A107: Total | N107: =SUM(B107:M107) -> 0 | P107: =SUM(P99:P106) -> 65259 | Q107: =SUM(Q99:Q103) -> 87036.49 | R107: =Q107-P107 -> 21777.49 | W107: =SUM(W99:W103) -> 53721.87 | X107: =SUM(X99:X103) -> 58599.53
A109: TOTALS | B109: JAN | C109: FEB | D109: MAR | E109: APR | F109: MAY | G109: JUN | H109: JUL | I109: AUG | J109: SEP | K109: OCT | L109: NOV | M109: DEC | N109: YEAR
A110: Total Income | C110: =tblIncome2833[[#Totals],[FEB]] -> 10951.16 | D110: =tblIncome2833[[#Totals],[MAR]] -> 3077 | E110: =tblIncome2833[[#Totals],[APR]] -> 6203.37 | F110: =tblIncome2833[[#Totals],[MAY]] -> 6143.99 | G110: =tblIncome2833[[#Totals],[JUN]] -> 6273.98 | H110: =tblIncome2833[[#Totals],[JUL]] -> 6101.1 | I110: =tblIncome2833[[#Totals],[AUG]] -> 0 | J110: =tblIncome2833[[#Totals],[SEP]] -> 0 | K110: =tblIncome2833[[#Totals],[OCT]] -> 0 | L110: =tblIncome2833[[#Totals],[NOV]] -> 0 | M110: =tblIncome2833[[#Totals],[DEC]] -> 0
A111: Total expenses | B111: =SUM(B22,B32,B38,B47,B55,B75,B84,B92,B96) -> 3054.72 | C111: =SUM(C22,C32,C38,C47,C55,C75,C84,C92,C96) -> 8114.19 | D111: =SUM(D22,D32,D38,D47,D55,D75,D84,D92,D96) -> 11912.8 | E111: =SUM(E22,E32,E38,E47,E55,E75,E84,E92,E96) -> 6137.66 | F111: =SUM(F22,F32,F38,F47,F55,F75,F84,F92,F96) -> 5825.41 | G111: =SUM(G22,G32,G38,G47,G55,G75,G84,G92,G96) -> 5436.4 | H111: =SUM(H22,H32,H38,H47,H55,H75,H84,H92,H96) -> 1197.11 | I111: =SUM(I22,I32,I38,I47,I55,I75,I84,I92,I96) -> 0 | J111: =SUM(J22,J32,J38,J47,J55,J75,J84,J92,J96) -> 0 | K111: =SUM(K22,K32,K38,K47,K55,K75,K84,K92) -> 0 | L111: =SUM(L22,L32,L38,L47,L55,L75,L84,L92) -> 0 | M111: =SUM(M22,M32,M38,M47,M55,M75,M84,M92) -> 0 | N111: =SUM(N22,N32,N38,N47,N55,N75,N84,N92) -> 41513.74
A112: Monthly Expenses | B112: =SUM(tblHome2941[[#Totals],[JAN]] + tblDaily3042[[#Totals],[JAN]] + tblTransportation3143[[#Totals],[JAN]] + tblEntertainment3244[[#Totals],[JAN]] + tblVacations3445[[#Totals],[JAN]]+ tblDues3647[[#Totals],[JAN]]+ tblPersonal3748[[#Totals],[JAN]]) -> 2011.72 | C112: =SUM(tblHome2941[[#Totals],[FEB]] + tblDaily3042[[#Totals],[FEB]] + tblTransportation3143[[#Totals],[FEB]] + tblEntertainment3244[[#Totals],[FEB]] + tblVacations3445[[#Totals],[FEB]]+ tblDues3647[[#Totals],[FEB]]+ tblPersonal3748[[#Totals],[FEB]]) -> 2603.68 | D112: =SUM(tblHome2941[[#Totals],[MAR]] + tblDaily3042[[#Totals],[MAR]] + tblTransportation3143[[#Totals],[MAR]] + tblEntertainment3244[[#Totals],[MAR]] + tblVacations3445[[#Totals],[MAR]]+ tblDues3647[[#Totals],[MAR]]+ tblPersonal3748[[#Totals],[MAR]]) -> 3046.28 | E112: =SUM(tblHome2941[[#Totals],[APR]] + tblDaily3042[[#Totals],[APR]] + tblTransportation3143[[#Totals],[APR]] + tblEntertainment3244[[#Totals],[APR]] + tblVacations3445[[#Totals],[APR]]+ tblDues3647[[#Totals],[APR]]+ tblPersonal3748[[#Totals],[APR]]) -> 1663.59 | F112: =SUM(tblHome2941[[#Totals],[MAY]] + tblDaily3042[[#Totals],[MAY]] + tblTransportation3143[[#Totals],[MAY]] + tblEntertainment3244[[#Totals],[MAY]] + tblVacations3445[[#Totals],[MAY]]+ tblDues3647[[#Totals],[MAY]]+ tblPersonal3748[[#Totals],[MAY]]) -> 1987.41 | G112: =SUM(tblHome2941[[#Totals],[JUN]] + tblDaily3042[[#Totals],[JUN]] + tblTransportation3143[[#Totals],[JUN]] + tblEntertainment3244[[#Totals],[JUN]] + tblVacations3445[[#Totals],[JUN]]+ tblDues3647[[#Totals],[JUN]]+ tblPersonal3748[[#Totals],[JUN]]) -> 1984.87 | H112: =SUM(tblHome2941[[#Totals],[JUL]] + tblDaily3042[[#Totals],[JUL]] + tblTransportation3143[[#Totals],[JUL]] + tblEntertainment3244[[#Totals],[JUL]] + tblVacations3445[[#Totals],[JUL]]+ tblDues3647[[#Totals],[JUL]]+ tblPersonal3748[[#Totals],[JUL]]) -> 505.12 | I112: =SUM(tblHome2941[[#Totals],[AUG]] + tblDaily3042[[#Totals],[AUG]] + tblTransportation3143[[#Totals],[AUG]] + tblEntertainment3244[[#Totals],[AUG]] + tblVacations3445[[#Totals],[AUG]]+ tblDues3647[[#Totals],[AUG]]+ tblPersonal3748[[#Totals],[AUG]]) -> 0 | J112: =SUM(tblHome2941[[#Totals],[SEP]] + tblDaily3042[[#Totals],[SEP]] + tblTransportation3143[[#Totals],[SEP]] + tblEntertainment3244[[#Totals],[SEP]] + tblVacations3445[[#Totals],[SEP]]+ tblDues3647[[#Totals],[SEP]]+ tblPersonal3748[[#Totals],[SEP]]) -> 0 | K112: =SUM(tblHome2941[[#Totals],[OCT]] + tblDaily3042[[#Totals],[OCT]] + tblTransportation3143[[#Totals],[OCT]] + tblEntertainment3244[[#Totals],[OCT]] + tblVacations3445[[#Totals],[OCT]]+ tblDues3647[[#Totals],[OCT]]+ tblPersonal3748[[#Totals],[OCT]]) -> 0 | L112: =SUM(tblHome2941[[#Totals],[NOV]] + tblDaily3042[[#Totals],[NOV]] + tblTransportation3143[[#Totals],[NOV]] + tblEntertainment3244[[#Totals],[NOV]] + tblVacations3445[[#Totals],[NOV]]+ tblDues3647[[#Totals],[NOV]]+ tblPersonal3748[[#Totals],[NOV]]) -> 0 | M112: =SUM(tblHome2941[[#Totals],[DEC]] + tblDaily3042[[#Totals],[DEC]] + tblTransportation3143[[#Totals],[DEC]] + tblEntertainment3244[[#Totals],[DEC]] + tblVacations3445[[#Totals],[DEC]]+ tblDues3647[[#Totals],[DEC]]+ tblPersonal3748[[#Totals],[DEC]]) -> 0 | N112: =SUM(tblHome2941[[#Totals],[YEAR]] + tblDaily3042[[#Totals],[YEAR]] + tblTransportation3143[[#Totals],[YEAR]] + tblEntertainment3244[[#Totals],[YEAR]] + tblVacations3445[[#Totals],[YEAR]]+ tblDues3647[[#Totals],[YEAR]]+ tblPersonal3748[[#Totals],[YEAR]]) -> 13802.67
A113: Cash In Bank | H113: =396.55+196.99 -> 593.54
A114: Actual cash spent
A115: chase bank | H115: 396.55
A116: Wells fargo | H116: 196.9
A117: Invested | B117: =SUM(tblRecreation3546[[#Totals],[JAN]]) -> 0 | C117: =SUM(tblRecreation3546[[#Totals],[FEB]]) -> 271.94 | D117: =SUM(tblRecreation3546[[#Totals],[MAR]]) -> 4444.49 | E117: =SUM(tblRecreation3546[[#Totals],[APR]]) -> 5816.06 | F117: =SUM(tblRecreation3546[[#Totals],[MAY]]) -> 188.86 | G117: =SUM(tblRecreation3546[[#Totals],[JUN]]) -> 45 | H117: =SUM(tblRecreation3546[[#Totals],[JUL]]) -> 559.81 | I117: =SUM(tblRecreation3546[[#Totals],[AUG]]) -> 0 | J117: =SUM(tblRecreation3546[[#Totals],[SEP]]) -> 0 | K117: =SUM(tblRecreation3546[[#Totals],[OCT]]) -> 0 | L117: =SUM(tblRecreation3546[[#Totals],[NOV]]) -> 0 | M117: =SUM(tblRecreation3546[[#Totals],[DEC]]) -> 0 | N117: =SUM(I117:M117) -> 0
...

Sheet 2026 Visualizations
A76: Category | B76: Jan | C76: Feb | D76: Mar | E76: Apr | F76: May | J76: Month | K76: Normal Spending | L76: Remittances
A77: Rent | B77: =SUM(tblHome2941[[#Totals],[JAN]]) -> 959 | C77: =SUM(tblHome2941[[#Totals],[FEB]]) -> 800 | D77: =SUM(tblHome2941[[#Totals],[MAR]]) -> 2196.03 | E77: =SUM(tblHome2941[[#Totals],[APR]]) -> 859.1 | F77: =SUM(tblHome2941[[#Totals],[MAY]]) -> 1547.96 | J77: Jan | K77: =SUM(B77:B84) -> 2011.72 | L77: =B85 -> 1043
A78: Grociers | B78: =SUM(tblDaily3042[[#Totals],[JAN]]) -> 494.25 | C78: =SUM(tblDaily3042[[#Totals],[FEB]]) -> 664.87 | D78: =SUM(tblDaily3042[[#Totals],[MAR]]) -> 173.96 | E78: =SUM(tblDaily3042[[#Totals],[APR]]) -> 386.66 | F78: =SUM(tblDaily3042[[#Totals],[MAY]]) -> 195.15 | J78: Feb | K78: =SUM(C77:C84) -> 2875.62 | L78: =C85 -> 5430.51
A79: Transportation | B79: =SUM(tblTransportation3143[[#Totals],[JAN]]) -> 4 | C79: =SUM(tblTransportation3143[[#Totals],[FEB]]) -> 64.68 | D79: =SUM(tblTransportation3143[[#Totals],[MAR]]) -> 24.75 | E79: =SUM(tblTransportation3143[[#Totals],[APR]]) -> 10.21 | F79: =SUM(tblTransportation3143[[#Totals],[MAY]]) -> 11.32 | J79: Mar | K79: =SUM(D77:D84) -> 7490.77 | L79: =D85 -> 8866.52
A80: Credit Card | B80: =SUM(tblEntertainment3244[[#Totals],[JAN]]) -> 56.95 | C80: =SUM(tblEntertainment3244[[#Totals],[FEB]]) -> 428.62 | D80: =SUM(tblEntertainment3244[[#Totals],[MAR]]) -> 500 | E80: =SUM(tblEntertainment3244[[#Totals],[APR]]) -> 200 | F80: =SUM(tblEntertainment3244[[#Totals],[MAY]]) -> 0 | J80: Apr | K80: =SUM(E77:E84) -> 7479.65 | L80: =E85 -> 4389.52
A81: Vacation | B81: =SUM(tblVacations3445[[#Totals],[JAN]]) -> 421 | C81: =SUM(tblVacations3445[[#Totals],[FEB]]) -> 586 | D81: =SUM(tblVacations3445[[#Totals],[MAR]]) -> 23.37 | E81: =SUM(tblVacations3445[[#Totals],[APR]]) -> 41 | F81: =SUM(tblVacations3445[[#Totals],[MAY]]) -> 0 | J81: May | K81: =SUM(F77:F84) -> 2176.27 | L81: =F85 -> 3838
A82: Investment | B82: =SUM(tblRecreation3546[[#Totals],[JAN]]) -> 0 | C82: =SUM(tblRecreation3546[[#Totals],[FEB]]) -> 271.94 | D82: =SUM(tblRecreation3546[[#Totals],[MAR]]) -> 4444.49 | E82: =SUM(tblRecreation3546[[#Totals],[APR]]) -> 5816.06 | F82: =SUM(tblRecreation3546[[#Totals],[MAY]]) -> 188.86
A83: Internet bills | B83: =SUM(tblDues3647[[#Totals],[JAN]]) -> 64.53 | C83: =SUM(tblDues3647[[#Totals],[FEB]]) -> 54.51 | D83: =SUM(tblDues3647[[#Totals],[MAR]]) -> 58.17 | E83: =SUM(tblDues3647[[#Totals],[APR]]) -> 58.32 | F83: =SUM(tblDues3647[[#Totals],[MAY]]) -> 59.53
A84: Self care | B84: =SUM(tblPersonal3748[[#Totals],[JAN]]) -> 11.99 | C84: =SUM(tblPersonal3748[[#Totals],[FEB]]) -> 5 | D84: =SUM(tblPersonal3748[[#Totals],[MAR]]) -> 70 | E84: =SUM(tblPersonal3748[[#Totals],[APR]]) -> 108.3 | F84: =SUM(tblPersonal3748[[#Totals],[MAY]]) -> 173.45
A85: Remitances | B85: =SUM(tblFinancial3849[[#Totals],[JAN]]) -> 1043 | C85: =SUM(tblFinancial3849[[#Totals],[FEB]]) -> 5430.51 | D85: =SUM(tblFinancial3849[[#Totals],[MAR]]) -> 8866.52 | E85: =SUM(tblFinancial3849[[#Totals],[APR]]) -> 4389.52 | F85: =SUM(tblFinancial3849[[#Totals],[MAY]]) -> 3838

Sheet 2025
B3: =SUM(tblHome29[AUG]) -> 494.95
A7: REVENUE
A8: INCOME | B8: JAN | C8: FEB | D8: MAR | E8: APR | F8: MAY | G8: JUN | H8: JUL | I8: AUG | J8: SEP | K8: OCT | L8: NOV | M8: DEC | N8: YEAR | O8: Last Updated on
A9: Wages Week 1 | I9: 2209.39 | J9: 2790.32 | K9: 2793.8 | L9: =1293.8+1500 -> 2793.8 | N9: =SUM(tblIncome28[[#This Row],[JAN]:[DEC]]) -> 10587.31 | O9: 45968
A10: Wages Week 2 | I10: 180.25 | J10: 2793 | K10: 2793.8 | L10: 1500 | N10: =SUM(tblIncome28[[#This Row],[JAN]:[DEC]]) -> 7267.05
A11: Wages Week 3 | I11: 2530.16 | N11: =SUM(tblIncome28[[#This Row],[JAN]:[DEC]]) -> 2530.16
A12: Wages Week 4 | I12: 3192.17 | N12: =SUM(tblIncome28[[#This Row],[JAN]:[DEC]]) -> 3192.17
A13: Total | B13: =SUBTOTAL(109,tblIncome28[JAN]) -> 0 | C13: =SUBTOTAL(109,tblIncome28[FEB]) -> 0 | D13: =SUBTOTAL(109,tblIncome28[MAR]) -> 0 | E13: =SUBTOTAL(109,tblIncome28[APR]) -> 0 | F13: =SUBTOTAL(109,tblIncome28[MAY]) -> 0 | G13: =SUBTOTAL(109,tblIncome28[JUN]) -> 0 | H13: =SUBTOTAL(109,tblIncome28[JUL]) -> 0 | I13: =SUBTOTAL(109,tblIncome28[AUG]) -> 8111.97 | J13: =SUBTOTAL(109,tblIncome28[SEP]) -> 5583.32 | K13: =SUBTOTAL(109,tblIncome28[OCT]) -> 5587.6 | L13: =SUBTOTAL(109,tblIncome28[NOV]) -> 4293.8 | M13: =SUBTOTAL(109,tblIncome28[DEC]) -> 0 | N13: =SUBTOTAL(109,tblIncome28[YEAR]) -> 23576.69
A15: EXPENSES
A16: HOME | B16: JAN | C16: FEB | D16: MAR | E16: APR | F16: MAY | G16: JUN | H16: JUL | I16: AUG | J16: SEP | K16: OCT | L16: NOV | M16: DEC | N16: YEAR | O16: Last Updated on
A17: Mortgage | I17: 450 | J17: 585 | K17: 550 | L17: 550 | N17: =SUM(tblHome29[[#This Row],[JAN]:[DEC]]) -> 2135 | O17: 45971
A18: Insurance | I18: 2.29 | N18: =SUM(tblHome29[[#This Row],[JAN]:[DEC]]) -> 2.29
A19: Deposit | J19: 550 | N19: =SUM(tblHome29[[#This Row],[JAN]:[DEC]]) -> 550
A20: Utilities | I20: 42.66 | K20: 29 | L20: 56.67 | N20: =SUM(tblHome29[[#This Row],[JAN]:[DEC]]) -> 128.33
A21: Total | B21: =SUBTOTAL(109,tblHome29[JAN]) -> 0 | C21: =SUBTOTAL(109,tblHome29[FEB]) -> 0 | D21: =SUBTOTAL(109,tblHome29[MAR]) -> 0 | E21: =SUBTOTAL(109,tblHome29[APR]) -> 0 | F21: =SUBTOTAL(109,tblHome29[MAY]) -> 0 | G21: =SUBTOTAL(109,tblHome29[JUN]) -> 0 | H21: =SUBTOTAL(109,tblHome29[JUL]) -> 0 | I21: =SUBTOTAL(109,tblHome29[AUG]) -> 494.95 | J21: =SUBTOTAL(109,tblHome29[SEP]) -> 1135 | K21: =SUBTOTAL(109,tblHome29[OCT]) -> 579 | L21: =SUBTOTAL(109,tblHome29[NOV]) -> 606.67 | M21: =SUBTOTAL(109,tblHome29[DEC]) -> 0 | N21: =SUBTOTAL(109,tblHome29[YEAR]) -> 2815.62
A23: DAILY LIVING | B23: JAN | C23: FEB | D23: MAR | E23: APR | F23: MAY | G23: JUN | H23: JUL | I23: AUG | J23: SEP | K23: OCT | L23: NOV | M23: DEC | N23: YEAR | O23: Last Updated on
A24: Split Wise | K24: 8.24 | N24: =SUM(tblDaily30[[#This Row],[JAN]:[DEC]]) -> 8.24 | O24: 45971
A25: Groceries | I25: 26 | J25: 73.34 | K25: =72.87 + 1.33 + 4.54 -> 78.74 | L25: =8.37 + 6.12 + 9.76 -> 24.25 | N25: =SUM(tblDaily30[[#This Row],[JAN]:[DEC]]) -> 202.33
A26: Dining out | I26: =15.49 + 21.59 -> 37.08 | J26: 53 | K26: 46.28 | L26: 6.95 | N26: =SUM(tblDaily30[[#This Row],[JAN]:[DEC]]) -> 143.31
A27: Other home expenses | I27: 130.61 | J27: 2.26 | N27: =SUM(tblDaily30[[#This Row],[JAN]:[DEC]]) -> 132.87
A28: Total | B28: =SUBTOTAL(109,tblDaily30[JAN]) -> 0 | C28: =SUBTOTAL(109,tblDaily30[FEB]) -> 0 | D28: =SUBTOTAL(109,tblDaily30[MAR]) -> 0 | E28: =SUBTOTAL(109,tblDaily30[APR]) -> 0 | F28: =SUBTOTAL(109,tblDaily30[MAY]) -> 0 | G28: =SUBTOTAL(109,tblDaily30[JUN]) -> 0 | H28: =SUBTOTAL(109,tblDaily30[JUL]) -> 0 | I28: =SUBTOTAL(109,tblDaily30[AUG]) -> 193.69 | J28: =SUBTOTAL(109,tblDaily30[SEP]) -> 128.6 | K28: =SUBTOTAL(109,tblDaily30[OCT]) -> 133.26 | L28: =SUBTOTAL(109,tblDaily30[NOV]) -> 31.2 | M28: =SUBTOTAL(109,tblDaily30[DEC]) -> 0 | N28: =SUBTOTAL(109,tblDaily30[YEAR]) -> 486.75
A30: TRANSPORTATION | B30: JAN | C30: FEB | D30: MAR | E30: APR | F30: MAY | G30: JUN | H30: JUL | I30: AUG | J30: SEP | K30: OCT | L30: NOV | M30: DEC | N30: YEAR | O30: Last Updated on
A31: Public transportation | I31: 101.25 | J31: 265.8 | N31: =SUM(tblTransportation31[[#This Row],[AUG]:[DEC]]) -> 367.05 | O31: 45971
A32: Friends transportation | H32: 15 | I32: 15 | N32: =SUM(tblTransportation31[[#This Row],[AUG]:[DEC]]) -> 15
A33: Cabs | J33: 16.15 | L33: 32 | N33: =SUM(tblTransportation31[[#This Row],[AUG]:[DEC]]) -> 48.15
A34: Total | B34: =SUBTOTAL(109,tblTransportation31[JAN]) -> 0 | C34: =SUBTOTAL(109,tblTransportation31[FEB]) -> 0 | D34: =SUBTOTAL(109,tblTransportation31[MAR]) -> 0 | E34: =SUBTOTAL(109,tblTransportation31[APR]) -> 0 | F34: =SUBTOTAL(109,tblTransportation31[MAY]) -> 0 | G34: =SUBTOTAL(109,tblTransportation31[JUN]) -> 0 | H34: =SUBTOTAL(109,tblTransportation31[JUL]) -> 15 | I34: =SUBTOTAL(109,tblTransportation31[AUG]) -> 116.25 | J34: =SUBTOTAL(109,tblTransportation31[SEP]) -> 281.95 | K34: =SUBTOTAL(109,tblTransportation31[OCT]) -> 0 | L34: =SUBTOTAL(109,tblTransportation31[NOV]) -> 32 | M34: =SUBTOTAL(109,tblTransportation31[DEC]) -> 0 | N34: =SUBTOTAL(109,tblTransportation31[YEAR]) -> 430.2
A36: Credit Card | B36: JAN | C36: FEB | D36: MAR | E36: APR | F36: MAY | G36: JUN | H36: JUL | I36: AUG | J36: SEP | K36: OCT | L36: NOV | M36: DEC | N36: YEAR | O36: Last Updated on | P36: Balance
A37: Chase | J37: 40 | K37: 41 | L37: 44 | N37: =SUM(tblEntertainment32[[#This Row],[JAN]:[DEC]]) -> 125 | O37: 45971 | P37: 4914.16
A38: Amex | I38: 95.25 | J38: 400 | K38: 1700 | L38: =200 + 400 + 300 -> 900 | N38: =SUM(tblEntertainment32[[#This Row],[JAN]:[DEC]]) -> 3095.25 | O38: Still pending few on 10th | P38: 2103
A39: Capital One | N39: =SUM(tblEntertainment32[[#This Row],[JAN]:[DEC]]) -> 0 | P39: 0
A40: Discover | I40: 0 | J40: 124 | N40: =SUM(tblEntertainment32[[#This Row],[JAN]:[DEC]]) -> 124 | P40: 1418
A41: Citi | I41: 0 | N41: =SUM(tblEntertainment32[[#This Row],[JAN]:[DEC]]) -> 0 | P41: 0
A42: BOFA | I42: 0 | N42: =SUM(tblEntertainment32[[#This Row],[JAN]:[DEC]]) -> 0
A43: Total | B43: =SUBTOTAL(109,tblEntertainment32[JAN]) -> 0 | C43: =SUBTOTAL(109,tblEntertainment32[FEB]) -> 0 | D43: =SUBTOTAL(109,tblEntertainment32[MAR]) -> 0 | E43: =SUBTOTAL(109,tblEntertainment32[APR]) -> 0 | F43: =SUBTOTAL(109,tblEntertainment32[MAY]) -> 0 | G43: =SUBTOTAL(109,tblEntertainment32[JUN]) -> 0 | H43: =SUBTOTAL(109,tblEntertainment32[JUL]) -> 0 | I43: =SUBTOTAL(109,tblEntertainment32[AUG]) -> 95.25 | J43: =SUBTOTAL(109,tblEntertainment32[SEP]) -> 564 | K43: =SUBTOTAL(109,tblEntertainment32[OCT]) -> 1741 | L43: =SUBTOTAL(109,tblEntertainment32[NOV]) -> 944 | M43: =SUBTOTAL(109,tblEntertainment32[DEC]) -> 0 | N43: =SUBTOTAL(109,tblEntertainment32[YEAR]) -> 3344.25 | P43: =SUM(tblEntertainment32[Balance]) -> 8435.16
A45: VACATIONS | B45: JAN | C45: FEB | D45: MAR | E45: APR | F45: MAY | G45: JUN | H45: JUL | I45: AUG | J45: SEP | K45: OCT | L45: NOV | M45: DEC | N45: YEAR | O45: Last Updated on
A46: Trips | L46: =157.46 + 69.46 -> 226.92 | N46: =SUM(tblVacations34[[#This Row],[JAN]:[DEC]]) -> 226.92 | O46: 45971
A47: Accommodations | N47: =SUM(tblVacations34[[#This Row],[JAN]:[DEC]]) -> 0
A48: Movies | I48: 26.49 | J48: 37.52 | K48: 26.49 | N48: =SUM(tblVacations34[[#This Row],[JAN]:[DEC]]) -> 90.5
A49: Airlines | I49: 80 | K49: 586 | N49: =SUM(tblVacations34[[#This Row],[JAN]:[DEC]]) -> 666
A50: Rental car | N50: =SUM(tblVacations34[[#This Row],[JAN]:[DEC]]) -> 0
A51: Total | B51: =SUBTOTAL(109,tblVacations34[JAN]) -> 0 | C51: =SUBTOTAL(109,tblVacations34[FEB]) -> 0 | D51: =SUBTOTAL(109,tblVacations34[MAR]) -> 0 | E51: =SUBTOTAL(109,tblVacations34[APR]) -> 0 | F51: =SUBTOTAL(109,tblVacations34[MAY]) -> 0 | G51: =SUBTOTAL(109,tblVacations34[JUN]) -> 0 | H51: =SUBTOTAL(109,tblVacations34[JUL]) -> 0 | I51: =SUM(tblVacations34[AUG]) -> 106.49 | J51: =SUBTOTAL(109,tblVacations34[SEP]) -> 37.52 | K51: =SUBTOTAL(109,tblVacations34[OCT]) -> 612.49 | L51: =SUBTOTAL(109,tblVacations34[NOV]) -> 226.92 | M51: =SUBTOTAL(109,tblVacations34[DEC]) -> 0 | N51: =SUBTOTAL(109,tblVacations34[YEAR]) -> 983.42
A53: Investment | B53: JAN | C53: FEB | D53: MAR | E53: APR | F53: MAY | G53: JUN | H53: JUL | I53: AUG | J53: SEP | K53: OCT | L53: NOV | M53: DEC | N53: Current Value | O53: Invested Total | P53: YEAR | Q53: Last Updated on
A54: Robinhood | I54: 872.95 | K54: 344 | L54: 155 | N54: 1049.46 | O54: =1112.85 + SUM(tblRecreation35[[#This Row],[AUG]:[DEC]]) -> 2484.8 | P54: =SUM(tblRecreation35[[#This Row],[JAN]:[DEC]]) -> 1371.95 | Q54: 45971
A55: Fidelity | I55: 30 | K55: 30 | N55: 1504.91 | O55: =1385.32 + SUM(tblRecreation35[[#This Row],[AUG]:[DEC]]) -> 1445.32 | P55: =SUM(tblRecreation35[[#This Row],[JAN]:[DEC]]) -> 60
A56: Angel One | I56: 79.93 | N56: 2773.36 | O56: =3148.9 + SUM(tblRecreation35[[#This Row],[AUG]:[DEC]]) -> 3228.83 | P56: =SUM(tblRecreation35[[#This Row],[JAN]:[DEC]]) -> 79.93
A57: Grow | I57: 285.46 | N57: 900.99 | O57: =715.33 + SUM(tblRecreation35[[#This Row],[AUG]:[DEC]]) -> 1000.79 | P57: =SUM(tblRecreation35[[#This Row],[JAN]:[DEC]]) -> 285.46
A58: Coinbase | I58: 0 | N58: 37.94 | O58: =42 + SUM(tblRecreation35[[#This Row],[AUG]:[DEC]]) -> 42 | P58: =SUM(tblRecreation35[[#This Row],[JAN]:[DEC]]) -> 0
A59: Coin DCX | I59: 0 | P59: =SUM(tblRecreation35[[#This Row],[JAN]:[DEC]]) -> 0
A60: Wazirx | I60: 0 | P60: =SUM(tblRecreation35[[#This Row],[JAN]:[DEC]]) -> 0
A61: Total | B61: =SUBTOTAL(109,tblRecreation35[JAN]) -> 0 | C61: =SUBTOTAL(109,tblRecreation35[FEB]) -> 0 | D61: =SUBTOTAL(109,tblRecreation35[MAR]) -> 0 | E61: =SUBTOTAL(109,tblRecreation35[APR]) -> 0 | F61: =SUBTOTAL(109,tblRecreation35[MAY]) -> 0 | G61: =SUBTOTAL(109,tblRecreation35[JUN]) -> 0 | H61: =SUBTOTAL(109,tblRecreation35[JUL]) -> 0 | I61: =SUBTOTAL(109,tblRecreation35[AUG]) -> 1268.34 | J61: =SUBTOTAL(109,tblRecreation35[SEP]) -> 0 | K61: =SUBTOTAL(109,tblRecreation35[OCT]) -> 374 | L61: =SUBTOTAL(109,tblRecreation35[NOV]) -> 155 | M61: =SUBTOTAL(109,tblRecreation35[DEC]) -> 0 | N61: =SUM(tblRecreation35[Current Value]) -> 6266.66 | O61: =SUM(tblRecreation35[Invested Total]) -> 8201.74 | P61: =SUBTOTAL(109,tblRecreation35[YEAR]) -> 1797.34
A63: DUES/SUBSCRIPTION | B63: JAN | C63: FEB | D63: MAR | E63: APR | F63: MAY | G63: JUN | H63: JUL | I63: AUG | J63: SEP | K63: OCT | L63: NOV | M63: DEC | N63: YEAR | O63: Last Updated on
A64: Internet connection | I64: 18.75 | J64: 41.81 | K64: 51.93 | N64: =SUM(tblDues36[[#This Row],[JAN]:[DEC]]) -> 112.49 | O64: 45979
A65: Wifi | I65: 4.57 | J65: 8 | K65: 8 | L65: 10 | M65: 10 | N65: =SUM(tblDues36[[#This Row],[JAN]:[DEC]]) -> 40.57
A66: Apple & Google One Subscriptions | J66: 2.35 | K66: 2.99 | L66: 2.99 | N66: =SUM(tblDues36[[#This Row],[JAN]:[DEC]]) -> 8.33
A67: Total | B67: =SUBTOTAL(109,tblDues36[JAN]) -> 0 | C67: =SUBTOTAL(109,tblDues36[FEB]) -> 0 | D67: =SUBTOTAL(109,tblDues36[MAR]) -> 0 | E67: =SUBTOTAL(109,tblDues36[APR]) -> 0 | F67: =SUBTOTAL(109,tblDues36[MAY]) -> 0 | G67: =SUBTOTAL(109,tblDues36[JUN]) -> 0 | H67: =SUBTOTAL(109,tblDues36[JUL]) -> 0 | I67: =SUBTOTAL(109,tblDues36[AUG]) -> 23.32 | J67: =SUBTOTAL(109,tblDues36[SEP]) -> 52.16 | K67: =SUBTOTAL(109,tblDues36[OCT]) -> 62.92 | L67: =SUBTOTAL(109,tblDues36[NOV]) -> 12.99 | M67: =SUBTOTAL(109,tblDues36[DEC]) -> 10 | N67: =SUBTOTAL(109,tblDues36[YEAR]) -> 161.39
A69: PERSONAL | B69: JAN | C69: FEB | D69: MAR | E69: APR | F69: MAY | G69: JUN | H69: JUL | I69: AUG | J69: SEP | K69: OCT | L69: NOV | M69: DEC | N69: YEAR | O69: Last Updated on
A70: Clothing | K70: 11.01 | N70: =SUM(tblPersonal37[[#This Row],[JAN]:[DEC]]) -> 11.01
A71: Gifts | N71: =SUM(tblPersonal37[[#This Row],[JAN]:[DEC]]) -> 0
A72: Salon/barber | I72: 12.99 | N72: =SUM(tblPersonal37[[#This Row],[JAN]:[DEC]]) -> 12.99
A73: Self Care (sunscreen, moisturizer) | K73: =45.15 +15.48 -> 60.63 | L73: =13.94 -> 13.94 | N73: =SUM(tblPersonal37[[#This Row],[JAN]:[DEC]]) -> 74.57
A74: Total | B74: =SUBTOTAL(109,tblPersonal37[JAN]) -> 0 | C74: =SUBTOTAL(109,tblPersonal37[FEB]) -> 0 | D74: =SUBTOTAL(109,tblPersonal37[MAR]) -> 0 | E74: =SUBTOTAL(109,tblPersonal37[APR]) -> 0 | F74: =SUBTOTAL(109,tblPersonal37[MAY]) -> 0 | G74: =SUBTOTAL(109,tblPersonal37[JUN]) -> 0 | H74: =SUBTOTAL(109,tblPersonal37[JUL]) -> 0 | I74: =SUBTOTAL(109,tblPersonal37[AUG]) -> 12.99 | J74: =SUBTOTAL(109,tblPersonal37[SEP]) -> 0 | K74: =SUBTOTAL(109,tblPersonal37[OCT]) -> 71.64 | L74: =SUBTOTAL(109,tblPersonal37[NOV]) -> 13.94 | M74: =SUBTOTAL(109,tblPersonal37[DEC]) -> 0 | N74: =SUBTOTAL(109,tblPersonal37[YEAR]) -> 98.57
A76: FINANCIAL OBLIGATIONS | B76: JAN | C76: FEB | D76: MAR | E76: APR | F76: MAY | G76: JUN | H76: JUL | I76: AUG | J76: SEP | K76: OCT | L76: NOV | M76: DEC | N76: YEAR | O76: Last Updated on | P76: Column1
A77: Family Loan Sendings | I77: =4204 - SUM(I56:I57) -> 3838.61 | J77: =4950 - SUM(J56:J57) -> 4950 | K77: =2900 -> 2900 | L77: =200+200+1000 -> 1400 | N77: =SUM(tblFinancial38[[#This Row],[JAN]:[DEC]]) -> 13088.61 | O77: 45971 | P77: Still pending few on 10th
A78: Income tax (additional) | N78: =SUM(tblFinancial38[[#This Row],[JAN]:[DEC]]) -> 0
A79: Other obligations (India ki family items) | K79: 64.72 | L79: =39.62 + 53.85 -> 93.47 | N79: =SUM(tblFinancial38[[#This Row],[JAN]:[DEC]]) -> 158.19
A80: Total | B80: =SUBTOTAL(109,tblFinancial38[JAN]) -> 0 | C80: =SUBTOTAL(109,tblFinancial38[FEB]) -> 0 | D80: =SUBTOTAL(109,tblFinancial38[MAR]) -> 0 | E80: =SUBTOTAL(109,tblFinancial38[APR]) -> 0 | F80: =SUBTOTAL(109,tblFinancial38[MAY]) -> 0 | G80: =SUBTOTAL(109,tblFinancial38[JUN]) -> 0 | H80: =SUBTOTAL(109,tblFinancial38[JUL]) -> 0 | I80: =SUBTOTAL(109,tblFinancial38[AUG]) -> 3838.61 | J80: =SUBTOTAL(109,tblFinancial38[SEP]) -> 4950 | K80: =SUBTOTAL(109,tblFinancial38[OCT]) -> 2964.72 | L80: =SUBTOTAL(109,tblFinancial38[NOV]) -> 1493.47 | M80: =SUBTOTAL(109,tblFinancial38[DEC]) -> 0 | N80: =SUBTOTAL(109,tblFinancial38[YEAR]) -> 13246.8
A82: MISC PAYMENTS | B82: JAN | C82: FEB | D82: MAR | E82: APR | F82: MAY | G82: JUN | H82: JUL | I82: AUG | J82: SEP | K82: OCT | L82: NOV | M82: DEC | N82: YEAR | O82: Last Updated on
A83: Other | N83: =SUM(tblMisc39[[#This Row],[JAN]:[DEC]]) -> 0
A84: Total | B84: =SUBTOTAL(109,tblMisc39[JAN]) -> 0 | C84: =SUBTOTAL(109,tblMisc39[FEB]) -> 0 | D84: =SUBTOTAL(109,tblMisc39[MAR]) -> 0 | E84: =SUBTOTAL(109,tblMisc39[APR]) -> 0 | F84: =SUBTOTAL(109,tblMisc39[MAY]) -> 0 | G84: =SUBTOTAL(109,tblMisc39[JUN]) -> 0 | H84: =SUBTOTAL(109,tblMisc39[JUL]) -> 0 | I84: =SUBTOTAL(109,tblMisc39[AUG]) -> 0 | J84: =SUBTOTAL(109,tblMisc39[SEP]) -> 0 | K84: =SUBTOTAL(109,tblMisc39[OCT]) -> 0 | L84: =SUBTOTAL(109,tblMisc39[NOV]) -> 0 | M84: =SUBTOTAL(109,tblMisc39[DEC]) -> 0 | N84: =SUBTOTAL(109,tblMisc39[YEAR]) -> 0
A86: Loan Payments | I86: Pending | J86: Total
A87: Home Loan | I87: 21237.06 | J87: 21237.06
A88: Education Loan | I88: 9220.79 | J88: 9220.79
A89: Gold Loan | I89: 16184.06 | J89: 16184.06
A90: Personal Loan | I90: 5065.96 | J90: 9943.62
A91: US Credit Cards | I91: =tblEntertainment32[[#Totals],[Balance]] -> 8435.16 | J91: =tblEntertainment32[[#Totals],[Balance]] -> 8435.16
A92: Total | I92: =SUM(I87:I91) -> 60143.03 | J92: =SUM(J87:J91) -> 65020.69
A94: TOTALS | B94: JAN | C94: FEB | D94: MAR | E94: APR | F94: MAY | G94: JUN | H94: JUL | I94: AUG | J94: SEP | K94: OCT | L94: NOV | M94: DEC | N94: YEAR
A95: Total expenses | B95: =SUM(tblMisc39[[#Totals],[JAN]],tblFinancial38[[#Totals],[JAN]],tblPersonal37[[#Totals],[JAN]],tblDues36[[#Totals],[JAN]],tblRecreation35[[#Totals],[JAN]],tblVacations34[[#Totals],[JAN]],#REF!,tblEntertainment32[[#Totals],[JAN]],tblTransportation31[[#Totals],[JAN]],tblDaily30[[#Totals],[JAN]],tblHome29[[#Totals],[JAN]]) -> #REF! | C95: =SUM(tblMisc39[[#Totals],[FEB]],tblFinancial38[[#Totals],[FEB]],tblPersonal37[[#Totals],[FEB]],tblDues36[[#Totals],[FEB]],tblRecreation35[[#Totals],[FEB]],tblVacations34[[#Totals],[FEB]],#REF!,tblEntertainment32[[#Totals],[FEB]],tblTransportation31[[#Totals],[FEB]],tblDaily30[[#Totals],[FEB]],tblHome29[[#Totals],[FEB]]) -> #REF! | D95: =SUM(tblMisc39[[#Totals],[MAR]],tblFinancial38[[#Totals],[MAR]],tblPersonal37[[#Totals],[MAR]],tblDues36[[#Totals],[MAR]],tblRecreation35[[#Totals],[MAR]],tblVacations34[[#Totals],[MAR]],#REF!,tblEntertainment32[[#Totals],[MAR]],tblTransportation31[[#Totals],[MAR]],tblDaily30[[#Totals],[MAR]],tblHome29[[#Totals],[MAR]]) -> #REF! | E95: =SUM(tblMisc39[[#Totals],[APR]],tblFinancial38[[#Totals],[APR]],tblPersonal37[[#Totals],[APR]],tblDues36[[#Totals],[APR]],tblRecreation35[[#Totals],[APR]],tblVacations34[[#Totals],[APR]],#REF!,tblEntertainment32[[#Totals],[APR]],tblTransportation31[[#Totals],[APR]],tblDaily30[[#Totals],[APR]],tblHome29[[#Totals],[APR]]) -> #REF! | F95: =SUM(tblMisc39[[#Totals],[MAY]],tblFinancial38[[#Totals],[MAY]],tblPersonal37[[#Totals],[MAY]],tblDues36[[#Totals],[MAY]],tblRecreation35[[#Totals],[MAY]],tblVacations34[[#Totals],[MAY]],#REF!,tblEntertainment32[[#Totals],[MAY]],tblTransportation31[[#Totals],[MAY]],tblDaily30[[#Totals],[MAY]],tblHome29[[#Totals],[MAY]]) -> #REF! | G95: =SUM(tblMisc39[[#Totals],[JUN]],tblFinancial38[[#Totals],[JUN]],tblPersonal37[[#Totals],[JUN]],tblDues36[[#Totals],[JUN]],tblRecreation35[[#Totals],[JUN]],tblVacations34[[#Totals],[JUN]],#REF!,tblEntertainment32[[#Totals],[JUN]],tblTransportation31[[#Totals],[JUN]],tblDaily30[[#Totals],[JUN]],tblHome29[[#Totals],[JUN]]) -> #REF! | H95: =SUM(tblMisc39[[#Totals],[JUL]],tblFinancial38[[#Totals],[JUL]],tblPersonal37[[#Totals],[JUL]],tblDues36[[#Totals],[JUL]],tblRecreation35[[#Totals],[JUL]],tblVacations34[[#Totals],[JUL]],#REF!,tblEntertainment32[[#Totals],[JUL]],tblTransportation31[[#Totals],[JUL]],tblDaily30[[#Totals],[JUL]],tblHome29[[#Totals],[JUL]]) -> #REF! | I95: =SUM(I21,I28,I34,I43,I51,I67,I74,I80,I84) -> 4881.55 | J95: =SUM(J21,J28,J34,J43,J51,J67,J74,J80,J84) -> 7149.23 | K95: =SUM(K21,K28,K34,K43,K51,K67,K74,K80) -> 6165.03 | L95: =SUM(L21,L28,L34,L43,L51,L67,L74,L80) -> 3361.19 | M95: =SUM(M21,M28,M34,M43,M51,M67,M74,M80) -> 10 | N95: =SUM(N21,N28,N34,N43,N51,N67,N74,N80) -> 21567
A96: Monthly Expenses | I96: =SUM(tblHome29[[#Totals],[AUG]] + tblDaily30[[#Totals],[AUG]] + tblTransportation31[[#Totals],[AUG]] + tblEntertainment32[[#Totals],[AUG]] + tblVacations34[[#Totals],[AUG]]+ tblDues36[[#Totals],[AUG]]+ tblPersonal37[[#Totals],[AUG]]) -> 1042.94 | J96: =SUM(tblHome29[[#Totals],[SEP]] + tblDaily30[[#Totals],[SEP]] + tblTransportation31[[#Totals],[SEP]] + tblEntertainment32[[#Totals],[SEP]] + tblVacations34[[#Totals],[SEP]]+ tblDues36[[#Totals],[SEP]]+ tblPersonal37[[#Totals],[SEP]]) -> 2199.23 | K96: =SUM(tblHome29[[#Totals],[OCT]] + tblDaily30[[#Totals],[OCT]] + tblTransportation31[[#Totals],[OCT]] + tblEntertainment32[[#Totals],[OCT]] + tblVacations34[[#Totals],[OCT]]+ tblDues36[[#Totals],[OCT]]+ tblPersonal37[[#Totals],[OCT]]) -> 3200.31 | L96: =SUM(tblHome29[[#Totals],[NOV]] + tblDaily30[[#Totals],[NOV]] + tblTransportation31[[#Totals],[NOV]] + tblEntertainment32[[#Totals],[NOV]] + tblVacations34[[#Totals],[NOV]]+ tblDues36[[#Totals],[NOV]]+ tblPersonal37[[#Totals],[NOV]]) -> 1867.72 | M96: =SUM(tblHome29[[#Totals],[DEC]] + tblDaily30[[#Totals],[DEC]] + tblTransportation31[[#Totals],[DEC]] + tblEntertainment32[[#Totals],[DEC]] + tblVacations34[[#Totals],[DEC]]+ tblDues36[[#Totals],[DEC]]+ tblPersonal37[[#Totals],[DEC]]) -> 10 | N96: =SUM(tblHome29[[#Totals],[YEAR]] + tblDaily30[[#Totals],[YEAR]] + tblTransportation31[[#Totals],[YEAR]] + tblEntertainment32[[#Totals],[YEAR]] + tblVacations34[[#Totals],[YEAR]]+ tblDues36[[#Totals],[YEAR]]+ tblPersonal37[[#Totals],[YEAR]]) -> 8320.2
A97: Invested | I97: =SUM(tblRecreation35[[#Totals],[AUG]]) -> 1268.34 | J97: =SUM(tblRecreation35[[#Totals],[SEP]]) -> 0 | K97: =SUM(tblRecreation35[[#Totals],[OCT]]) -> 374 | L97: =SUM(tblRecreation35[[#Totals],[NOV]]) -> 155 | M97: =SUM(tblRecreation35[[#Totals],[DEC]]) -> 0 | N97: =SUM(I97:M97) -> 1797.34
A100: Debt | I100: =I92 -> 60143.03

Sheet 2025 Visualizations
A23: Category | B23: Aug | C23: Sept | D23: OCT | E23: Nov | F23: Dec
A24: Rent | B24: =SUM(tblHome29[AUG]) -> 494.95 | C24: =SUM(tblHome29[SEP]) -> 1135 | D24: =SUM(tblHome29[OCT]) -> 579 | E24: =SUM(tblHome29[NOV]) -> 606.67 | F24: =SUM(tblHome29[DEC]) -> 0
A25: Grociers | B25: =SUM(tblDaily30[AUG]) -> 193.69 | C25: =SUM(tblDaily30[SEP]) -> 128.6 | D25: =SUM(tblDaily30[OCT]) -> 133.26 | E25: =SUM(tblDaily30[NOV]) -> 31.2 | F25: =SUM(tblDaily30[DEC]) -> 0
A26: Transportation | B26: =SUM(tblTransportation31[AUG]) -> 116.25 | C26: =SUM(tblTransportation31[SEP]) -> 281.95 | D26: =SUM(tblTransportation31[OCT]) -> 0 | E26: =SUM(tblTransportation31[NOV]) -> 32 | F26: =SUM(tblTransportation31[DEC]) -> 0
A27: Credit Card | B27: =SUM(tblEntertainment32[AUG]) -> 95.25 | C27: =SUM(tblEntertainment32[SEP]) -> 564 | D27: =SUM(tblEntertainment32[OCT]) -> 1741 | E27: =SUM(tblEntertainment32[NOV]) -> 944 | F27: =SUM(tblEntertainment32[DEC]) -> 0
A28: Vacation | B28: =SUM(tblVacations34[AUG]) -> 106.49 | C28: =SUM(tblVacations34[SEP]) -> 37.52 | D28: =SUM(tblVacations34[OCT]) -> 612.49 | E28: =SUM(tblVacations34[NOV]) -> 226.92 | F28: =SUM(tblVacations34[DEC]) -> 0
A29: Investment | B29: =SUM(tblRecreation35[AUG]) -> 1268.34 | C29: =SUM(tblRecreation35[SEP]) -> 0 | D29: =SUM(tblRecreation35[OCT]) -> 374 | E29: =SUM(tblRecreation35[NOV]) -> 155 | F29: =SUM(tblRecreation35[DEC]) -> 0
A30: Internet bills | B30: =SUM(tblDues36[AUG]) -> 23.32 | C30: =SUM(tblDues36[SEP]) -> 52.16 | D30: =SUM(tblDues36[OCT]) -> 62.92 | E30: =SUM(tblDues36[NOV]) -> 12.99 | F30: =SUM(tblDues36[DEC]) -> 10
A31: Self care | B31: =SUM(tblPersonal37[AUG]) -> 12.99 | C31: =SUM(tblPersonal37[SEP]) -> 0 | D31: =SUM(tblPersonal37[OCT]) -> 71.64 | E31: =SUM(tblPersonal37[NOV]) -> 13.94 | F31: =SUM(tblPersonal37[DEC]) -> 0
A32: Remitances | B32: =SUM(tblFinancial38[AUG]) -> 3838.61 | C32: =SUM(tblFinancial38[SEP]) -> 4950 | D32: =SUM(tblFinancial38[OCT]) -> 2964.72 | E32: =SUM(tblFinancial38[NOV]) -> 1493.47 | F32: =SUM(tblFinancial38[DEC]) -> 0
A35: Month | B35: Normal Spending | C35: Remittances
A36: Aug | B36: =SUM(B23:B31) -> 2311.28 | C36: =B32 -> 3838.61
A37: Sept | B37: =SUM(C23:C31) -> 2199.23 | C37: =C32 -> 4950
A38: Oct | B38: =SUM(D23:D31) -> 3574.31 | C38: =D32 -> 2964.72
A39: Nov | B39: =SUM(E23:E31) -> 2022.72 | C39: =E32 -> 1493.47
A40: Dec | B40: =SUM(F23:F31) -> 10 | C40: =F32 -> 0

Sheet Sheet1
A1: BUDGET WHEEL
A2: Monthly income | F2: Savings amount
A3: 5738 | F3: =Savings -> 2577
F5: Value calculated automatically

Sheet Personal net worth
M1: Cash and Cash Equivalent | N1: =SUMIF(#REF!,'[2]Personal net worth'!M1,#REF!)+ROW(M1)/10000 -> #REF! | O1: =_xlfn.RANK.EQ(N1,$N$1:$N$5,0) -> #REF! | Q1: =INDEX($M$1:$N$5,MATCH(5,$O$1:$O$5,0),1) -> #N/A | R1: =ROUND(INDEX($M$1:$N$5,MATCH(5,$O$1:$O$5,0),2),2) -> #N/A | T1: Total Assets | U1: =SUM(#REF!) -> #REF!
M2: Properties | N2: =SUMIF(#REF!,'[2]Personal net worth'!M2,#REF!)+ROW(M2)/10000 -> #REF! | O2: =_xlfn.RANK.EQ(N2,$N$1:$N$5,0) -> #REF! | Q2: =INDEX($M$1:$N$5,MATCH(4,$O$1:$O$5,0),1) -> #N/A | R2: =ROUND(INDEX($M$1:$N$5,MATCH(4,$O$1:$O$5,0),2),2) -> #N/A | T2: Total Debts | U2: =SUM(#REF!) -> #REF!
C3: PERSONAL NET WORTH | G3: ASSETS VS DEBT | M3: Investments | N3: =SUMIF(#REF!,'[2]Personal net worth'!M3,#REF!)+ROW(M3)/10000 -> #REF! | O3: =_xlfn.RANK.EQ(N3,$N$1:$N$5,0) -> #REF! | Q3: =INDEX($M$1:$N$5,MATCH(3,$O$1:$O$5,0),1) -> #N/A | R3: =ROUND(INDEX($M$1:$N$5,MATCH(3,$O$1:$O$5,0),2),2) -> #N/A
C4: =E5-E7 -> #REF! | M4: Retirement Savings | N4: =SUMIF(#REF!,'[2]Personal net worth'!M4,#REF!)+ROW(M4)/10000 -> #REF! | O4: =_xlfn.RANK.EQ(N4,$N$1:$N$5,0) -> #REF! | Q4: =INDEX($M$1:$N$5,MATCH(2,$O$1:$O$5,0),1) -> #N/A | R4: =ROUND(INDEX($M$1:$N$5,MATCH(2,$O$1:$O$5,0),2),2) -> #N/A
D5: Total assets | E5: =SUM(#REF!) -> #REF! | M5: Life Insurance | N5: =SUMIF(#REF!,'[2]Personal net worth'!M5,#REF!)+ROW(M5)/10000 -> #REF! | O5: =_xlfn.RANK.EQ(N5,$N$1:$N$5,0) -> #REF! | Q5: =INDEX($M$1:$N$5,MATCH(1,$O$1:$O$5,0),1) -> #N/A | R5: =ROUND(INDEX($M$1:$N$5,MATCH(1,$O$1:$O$5,0),2),2) -> #N/A
D7: Total debt | E7: =SUM(#REF!) -> #REF!
C9: SUMMARY OF ASSETS
H11: =Q5 -> #N/A | I11: =R5 -> #N/A
H13: =Q4 -> #N/A | I13: =R4 -> #N/A
H15: =Q3 -> #N/A | I15: =R3 -> #N/A
H17: =Q2 -> #N/A | I17: =R2 -> #N/A
H19: =Q1 -> #N/A | I19: =R1 -> #N/A

Sheet New Sheet
B3: =SUM(tblHome29413[AUG]) -> 0
A7: REVENUE
A8: INCOME | B8: JAN | C8: FEB | D8: MAR | E8: APR | F8: MAY | G8: JUN | H8: JUL | I8: AUG | J8: SEP | K8: OCT | L8: NOV | M8: DEC | N8: YEAR | O8: Last Updated on
A9: Wages Week 1 | B9: 1600 | N9: =SUM(tblIncome28332[[#This Row],[JAN]:[DEC]]) -> 1600 | O9: 46058
A10: Wages Week 2 | N10: =SUM(tblIncome28332[[#This Row],[JAN]:[DEC]]) -> 0
A11: Wages Week 3 | N11: =SUM(tblIncome28332[[#This Row],[JAN]:[DEC]]) -> 0
A12: Wages Week 4 | N12: =SUM(tblIncome28332[[#This Row],[JAN]:[DEC]]) -> 0
A13: Total | B13: =SUBTOTAL(109,tblIncome28332[JAN]) -> 1600 | C13: =SUBTOTAL(109,tblIncome28332[FEB]) -> 0 | D13: =SUBTOTAL(109,tblIncome28332[MAR]) -> 0 | E13: =SUBTOTAL(109,tblIncome28332[APR]) -> 0 | F13: =SUBTOTAL(109,tblIncome28332[MAY]) -> 0 | G13: =SUBTOTAL(109,tblIncome28332[JUN]) -> 0 | H13: =SUBTOTAL(109,tblIncome28332[JUL]) -> 0 | I13: =SUBTOTAL(109,tblIncome28332[AUG]) -> 0 | J13: =SUBTOTAL(109,tblIncome28332[SEP]) -> 0 | K13: =SUBTOTAL(109,tblIncome28332[OCT]) -> 0 | L13: =SUBTOTAL(109,tblIncome28332[NOV]) -> 0 | M13: =SUBTOTAL(109,tblIncome28332[DEC]) -> 0 | N13: =SUBTOTAL(109,tblIncome28332[YEAR]) -> 1600
A15: EXPENSES
A16: HOME | B16: JAN | C16: FEB | D16: MAR | E16: APR | F16: MAY | G16: JUN | H16: JUL | I16: AUG | J16: SEP | K16: OCT | L16: NOV | M16: DEC | N16: YEAR | O16: Last Updated on
A17: Mortgage | B17: 850 | N17: =SUM(tblHome29413[[#This Row],[JAN]:[DEC]]) -> 850 | O17: 46058
A18: Insurance | N18: =SUM(tblHome29413[[#This Row],[JAN]:[DEC]]) -> 0
A19: Deposit | N19: =SUM(tblHome29413[[#This Row],[JAN]:[DEC]]) -> 0
A20: Utilities | B20: 109 | N20: =SUM(tblHome29413[[#This Row],[JAN]:[DEC]]) -> 109
A21: Total | B21: =SUBTOTAL(109,tblHome29413[JAN]) -> 959 | C21: =SUBTOTAL(109,tblHome29413[FEB]) -> 0 | D21: =SUBTOTAL(109,tblHome29413[MAR]) -> 0 | E21: =SUBTOTAL(109,tblHome29413[APR]) -> 0 | F21: =SUBTOTAL(109,tblHome29413[MAY]) -> 0 | G21: =SUBTOTAL(109,tblHome29413[JUN]) -> 0 | H21: =SUBTOTAL(109,tblHome29413[JUL]) -> 0 | I21: =SUBTOTAL(109,tblHome29413[AUG]) -> 0 | J21: =SUBTOTAL(109,tblHome29413[SEP]) -> 0 | K21: =SUBTOTAL(109,tblHome29413[OCT]) -> 0 | L21: =SUBTOTAL(109,tblHome29413[NOV]) -> 0 | M21: =SUBTOTAL(109,tblHome29413[DEC]) -> 0 | N21: =SUBTOTAL(109,tblHome29413[YEAR]) -> 959
A23: DAILY LIVING | B23: JAN | C23: FEB | D23: MAR | E23: APR | F23: MAY | G23: JUN | H23: JUL | I23: AUG | J23: SEP | K23: OCT | L23: NOV | M23: DEC | N23: YEAR | O23: Last Updated on
A24: Split Wise | B24: 90 | N24: =SUM(tblDaily30424[[#This Row],[JAN]:[DEC]]) -> 90 | O24: 46058
A25: Groceries | B25: 308 | C25: 69 | N25: =SUM(tblDaily30424[[#This Row],[JAN]:[DEC]]) -> 377
A26: Dining out | N26: =SUM(tblDaily30424[[#This Row],[JAN]:[DEC]]) -> 0
A27: Other home expenses (Amazon) | B27: 96.25 | C27: 48 | N27: =SUM(tblDaily30424[[#This Row],[JAN]:[DEC]]) -> 144.25
A28: Total | B28: =SUBTOTAL(109,tblDaily30424[JAN]) -> 494.25 | C28: =SUBTOTAL(109,tblDaily30424[FEB]) -> 117 | D28: =SUBTOTAL(109,tblDaily30424[MAR]) -> 0 | E28: =SUBTOTAL(109,tblDaily30424[APR]) -> 0 | F28: =SUBTOTAL(109,tblDaily30424[MAY]) -> 0 | G28: =SUBTOTAL(109,tblDaily30424[JUN]) -> 0 | H28: =SUBTOTAL(109,tblDaily30424[JUL]) -> 0 | I28: =SUBTOTAL(109,tblDaily30424[AUG]) -> 0 | J28: =SUBTOTAL(109,tblDaily30424[SEP]) -> 0 | K28: =SUBTOTAL(109,tblDaily30424[OCT]) -> 0 | L28: =SUBTOTAL(109,tblDaily30424[NOV]) -> 0 | M28: =SUBTOTAL(109,tblDaily30424[DEC]) -> 0 | N28: =SUBTOTAL(109,tblDaily30424[YEAR]) -> 611.25
A30: TRANSPORTATION | B30: JAN | C30: FEB | D30: MAR | E30: APR | F30: MAY | G30: JUN | H30: JUL | I30: AUG | J30: SEP | K30: OCT | L30: NOV | M30: DEC | N30: YEAR | O30: Last Updated on
A31: Public transportation | B31: 4 | N31: =SUM(tblTransportation31435[[#This Row],[JAN]:[DEC]]) -> 4 | O31: 46058
A32: Friends transportation | N32: =SUM(tblTransportation31435[[#This Row],[JAN]:[DEC]]) -> 0
A33: Cabs | N33: =SUM(tblTransportation31435[[#This Row],[JAN]:[DEC]]) -> 0
A34: Total | B34: =SUBTOTAL(109,tblTransportation31435[JAN]) -> 4 | C34: =SUBTOTAL(109,tblTransportation31435[FEB]) -> 0 | D34: =SUBTOTAL(109,tblTransportation31435[MAR]) -> 0 | E34: =SUBTOTAL(109,tblTransportation31435[APR]) -> 0 | F34: =SUBTOTAL(109,tblTransportation31435[MAY]) -> 0 | G34: =SUBTOTAL(109,tblTransportation31435[JUN]) -> 0 | H34: =SUBTOTAL(109,tblTransportation31435[JUL]) -> 0 | I34: =SUBTOTAL(109,tblTransportation31435[AUG]) -> 0 | J34: =SUBTOTAL(109,tblTransportation31435[SEP]) -> 0 | K34: =SUBTOTAL(109,tblTransportation31435[OCT]) -> 0 | L34: =SUBTOTAL(109,tblTransportation31435[NOV]) -> 0 | M34: =SUBTOTAL(109,tblTransportation31435[DEC]) -> 0 | N34: =SUBTOTAL(109,tblTransportation31435[YEAR]) -> 4
A36: Credit Card | B36: JAN | C36: FEB | D36: MAR | E36: APR | F36: MAY | G36: JUN | H36: JUL | I36: AUG | J36: SEP | K36: OCT | L36: NOV | M36: DEC | N36: YEAR | O36: Last Updated on | P36: Balance
A37: Chase | B37: 48 | C37: 52 | N37: =SUM(tblEntertainment32446[[#This Row],[JAN]:[DEC]]) -> 100 | O37: 46058 | P37: 5539
A38: Amex | B38: 8.95 | N38: =SUM(tblEntertainment32446[[#This Row],[JAN]:[DEC]]) -> 8.95 | P38: 0
A39: Capital One | N39: =SUM(tblEntertainment32446[[#This Row],[JAN]:[DEC]]) -> 0 | P39: 0
A40: Discover | N40: =SUM(tblEntertainment32446[[#This Row],[JAN]:[DEC]]) -> 0 | P40: 2123
A41: Citi | N41: =SUM(tblEntertainment32446[[#This Row],[JAN]:[DEC]]) -> 0 | P41: 0
A42: BOFA | N42: =SUM(tblEntertainment32446[[#This Row],[JAN]:[DEC]]) -> 0
A43: Total | B43: =SUBTOTAL(109,tblEntertainment32446[JAN]) -> 56.95 | C43: =SUBTOTAL(109,tblEntertainment32446[FEB]) -> 52 | D43: =SUBTOTAL(109,tblEntertainment32446[MAR]) -> 0 | E43: =SUBTOTAL(109,tblEntertainment32446[APR]) -> 0 | F43: =SUBTOTAL(109,tblEntertainment32446[MAY]) -> 0 | G43: =SUBTOTAL(109,tblEntertainment32446[JUN]) -> 0 | H43: =SUBTOTAL(109,tblEntertainment32446[JUL]) -> 0 | I43: =SUBTOTAL(109,tblEntertainment32446[AUG]) -> 0 | J43: =SUBTOTAL(109,tblEntertainment32446[SEP]) -> 0 | K43: =SUBTOTAL(109,tblEntertainment32446[OCT]) -> 0 | L43: =SUBTOTAL(109,tblEntertainment32446[NOV]) -> 0 | M43: =SUBTOTAL(109,tblEntertainment32446[DEC]) -> 0 | N43: =SUBTOTAL(109,tblEntertainment32446[YEAR]) -> 108.95 | P43: =SUM(tblEntertainment32446[Balance]) -> 7662
A45: VACATIONS | B45: JAN | C45: FEB | D45: MAR | E45: APR | F45: MAY | G45: JUN | H45: JUL | I45: AUG | J45: SEP | K45: OCT | L45: NOV | M45: DEC | N45: YEAR | O45: Last Updated on
A46: Trips | N46: =SUM(tblVacations34457[[#This Row],[JAN]:[DEC]]) -> 0
A47: Accommodations | N47: =SUM(tblVacations34457[[#This Row],[JAN]:[DEC]]) -> 0 | O47: 46058
A48: Movies | N48: =SUM(tblVacations34457[[#This Row],[JAN]:[DEC]]) -> 0
A49: Airlines | B49: 421 | N49: =SUM(tblVacations34457[[#This Row],[JAN]:[DEC]]) -> 421
A50: Rental car | N50: =SUM(tblVacations34457[[#This Row],[JAN]:[DEC]]) -> 0
A51: Total | B51: =SUBTOTAL(109,tblVacations34457[JAN]) -> 421 | C51: =SUBTOTAL(109,tblVacations34457[FEB]) -> 0 | D51: =SUBTOTAL(109,tblVacations34457[MAR]) -> 0 | E51: =SUBTOTAL(109,tblVacations34457[APR]) -> 0 | F51: =SUBTOTAL(109,tblVacations34457[MAY]) -> 0 | G51: =SUBTOTAL(109,tblVacations34457[JUN]) -> 0 | H51: =SUBTOTAL(109,tblVacations34457[JUL]) -> 0 | I51: =SUM(tblVacations34457[AUG]) -> 0 | J51: =SUBTOTAL(109,tblVacations34457[SEP]) -> 0 | K51: =SUBTOTAL(109,tblVacations34457[OCT]) -> 0 | L51: =SUBTOTAL(109,tblVacations34457[NOV]) -> 0 | M51: =SUBTOTAL(109,tblVacations34457[DEC]) -> 0 | N51: =SUBTOTAL(109,tblVacations34457[YEAR]) -> 421
A53: Investment | B53: JAN | C53: FEB | D53: MAR | E53: APR | F53: MAY | G53: JUN | H53: JUL | I53: AUG | J53: SEP | K53: OCT | L53: NOV | M53: DEC | N53: Current Value | O53: Invested Total | P53: YEAR | Q53: Last Updated on
A54: Robinhood | O54: =2733+SUM(tblRecreation35468[[#This Row],[JAN]:[JUN]]) -> 2733 | P54: =SUM(tblRecreation35468[[#This Row],[JAN]:[DEC]]) -> 0 | Q54: 46058
A55: Fidelity | O55: =1381 +SUM(tblRecreation35468[[#This Row],[JAN]:[JUN]]) -> 1381 | P55: =SUM(tblRecreation35468[[#This Row],[JAN]:[DEC]]) -> 0
A56: Angel One | O56: =3092+ SUM(tblRecreation35468[[#This Row],[JAN]:[JUN]]) -> 3092 | P56: =SUM(tblRecreation35468[[#This Row],[JAN]:[DEC]]) -> 0
A57: Coin by Zerodha MF | O57: =155 + SUM(tblRecreation35468[[#This Row],[JAN]:[JUN]]) -> 155 | P57: =SUM(tblRecreation35468[[#This Row],[JAN]:[DEC]]) -> 0
A58: Zerodha | O58: =155+SUM(tblRecreation35468[[#This Row],[JAN]:[JUN]]) -> 155 | P58: =SUM(tblRecreation35468[[#This Row],[JAN]:[DEC]]) -> 0
A59: Grow | O59: =1079+ SUM(tblRecreation35468[[#This Row],[JAN]:[JUN]]) -> 1079 | P59: =SUM(tblRecreation35468[[#This Row],[JAN]:[DEC]]) -> 0
A60: Coinbase | O60: =42+SUM(tblRecreation35468[[#This Row],[JAN]:[JUN]]) -> 42 | P60: =SUM(tblRecreation35468[[#This Row],[JAN]:[DEC]]) -> 0
A61: Coin DCX | O61: =SUM(tblRecreation35468[[#This Row],[JAN]:[DEC]]) -> 0 | P61: =SUM(tblRecreation35468[[#This Row],[JAN]:[DEC]]) -> 0
A62: Wazirx | O62: =SUM(tblRecreation35468[[#This Row],[JAN]:[DEC]]) -> 0 | P62: =SUM(tblRecreation35468[[#This Row],[JAN]:[DEC]]) -> 0
A63: Total | B63: =SUBTOTAL(109,tblRecreation35468[JAN]) -> 0 | C63: =SUBTOTAL(109,tblRecreation35468[FEB]) -> 0 | D63: =SUBTOTAL(109,tblRecreation35468[MAR]) -> 0 | E63: =SUBTOTAL(109,tblRecreation35468[APR]) -> 0 | F63: =SUBTOTAL(109,tblRecreation35468[MAY]) -> 0 | G63: =SUBTOTAL(109,tblRecreation35468[JUN]) -> 0 | H63: =SUBTOTAL(109,tblRecreation35468[JUL]) -> 0 | I63: =SUBTOTAL(109,tblRecreation35468[AUG]) -> 0 | J63: =SUBTOTAL(109,tblRecreation35468[SEP]) -> 0 | K63: =SUBTOTAL(109,tblRecreation35468[OCT]) -> 0 | L63: =SUBTOTAL(109,tblRecreation35468[NOV]) -> 0 | M63: =SUBTOTAL(109,tblRecreation35468[DEC]) -> 0 | N63: =SUM(tblRecreation35468[Current Value]) -> 0 | O63: =SUM(tblRecreation35468[Invested Total]) -> 8637 | P63: =SUBTOTAL(109,tblRecreation35468[YEAR]) -> 0
A65: DUES/SUBSCRIPTION | B65: JAN | C65: FEB | D65: MAR | E65: APR | F65: MAY | G65: JUN | H65: JUL | I65: AUG | J65: SEP | K65: OCT | L65: NOV | M65: DEC | N65: YEAR | O65: Last Updated on
A66: Internet connection | B66: 51.54 | N66: =SUM(tblDues36479[[#This Row],[JAN]:[DEC]]) -> 51.54 | O66: 46058
A67: Wifi | N67: =SUM(tblDues36479[[#This Row],[JAN]:[DEC]]) -> 0
A68: Apple & Google One Subscriptions | B68: 2.99 | C68: 2.99 | N68: =SUM(tblDues36479[[#This Row],[JAN]:[DEC]]) -> 5.98
A69: Total | B69: =SUBTOTAL(109,tblDues36479[JAN]) -> 54.53 | C69: =SUBTOTAL(109,tblDues36479[FEB]) -> 2.99 | D69: =SUBTOTAL(109,tblDues36479[MAR]) -> 0 | E69: =SUBTOTAL(109,tblDues36479[APR]) -> 0 | F69: =SUBTOTAL(109,tblDues36479[MAY]) -> 0 | G69: =SUBTOTAL(109,tblDues36479[JUN]) -> 0 | H69: =SUBTOTAL(109,tblDues36479[JUL]) -> 0 | I69: =SUBTOTAL(109,tblDues36479[AUG]) -> 0 | J69: =SUBTOTAL(109,tblDues36479[SEP]) -> 0 | K69: =SUBTOTAL(109,tblDues36479[OCT]) -> 0 | L69: =SUBTOTAL(109,tblDues36479[NOV]) -> 0 | M69: =SUBTOTAL(109,tblDues36479[DEC]) -> 0 | N69: =SUBTOTAL(109,tblDues36479[YEAR]) -> 57.52
A71: PERSONAL | B71: JAN | C71: FEB | D71: MAR | E71: APR | F71: MAY | G71: JUN | H71: JUL | I71: AUG | J71: SEP | K71: OCT | L71: NOV | M71: DEC | N71: YEAR | O71: Last Updated on
A72: Clothing | N72: =SUM(tblPersonal374810[[#This Row],[JAN]:[DEC]]) -> 0 | O72: 46058
A73: Gifts | N73: =SUM(tblPersonal374810[[#This Row],[JAN]:[DEC]]) -> 0
A74: Salon/barber | B74: 11.99 | N74: =SUM(tblPersonal374810[[#This Row],[JAN]:[DEC]]) -> 11.99
A75: Self Care (sunscreen, moisturizer) | N75: =SUM(tblPersonal374810[[#This Row],[JAN]:[DEC]]) -> 0
A76: Total | B76: =SUBTOTAL(109,tblPersonal374810[JAN]) -> 11.99 | C76: =SUBTOTAL(109,tblPersonal374810[FEB]) -> 0 | D76: =SUBTOTAL(109,tblPersonal374810[MAR]) -> 0 | E76: =SUBTOTAL(109,tblPersonal374810[APR]) -> 0 | F76: =SUBTOTAL(109,tblPersonal374810[MAY]) -> 0 | G76: =SUBTOTAL(109,tblPersonal374810[JUN]) -> 0 | H76: =SUBTOTAL(109,tblPersonal374810[JUL]) -> 0 | I76: =SUBTOTAL(109,tblPersonal374810[AUG]) -> 0 | J76: =SUBTOTAL(109,tblPersonal374810[SEP]) -> 0 | K76: =SUBTOTAL(109,tblPersonal374810[OCT]) -> 0 | L76: =SUBTOTAL(109,tblPersonal374810[NOV]) -> 0 | M76: =SUBTOTAL(109,tblPersonal374810[DEC]) -> 0 | N76: =SUBTOTAL(109,tblPersonal374810[YEAR]) -> 11.99
A78: FINANCIAL OBLIGATIONS | B78: JAN | C78: FEB | D78: MAR | E78: APR | F78: MAY | G78: JUN | H78: JUL | I78: AUG | J78: SEP | K78: OCT | L78: NOV | M78: DEC | N78: YEAR | O78: Last Updated on | P78: Column1
A79: Family Loan Sendings | B79: 1000 | N79: =SUM(tblFinancial384911[[#This Row],[JAN]:[DEC]]) -> 1000 | O79: 46058
A80: Income tax (additional) | C80: 150 | N80: =SUM(tblFinancial384911[[#This Row],[JAN]:[DEC]]) -> 150
A81: Second Masters | B81: 43 | N81: =SUM(tblFinancial384911[[#This Row],[JAN]:[DEC]]) -> 43
A82: Other obligations (India ki family items) | N82: =SUM(tblFinancial384911[[#This Row],[JAN]:[DEC]]) -> 0
A83: Total | B83: =SUBTOTAL(109,tblFinancial384911[JAN]) -> 1043 | C83: =SUBTOTAL(109,tblFinancial384911[FEB]) -> 150 | D83: =SUBTOTAL(109,tblFinancial384911[MAR]) -> 0 | E83: =SUBTOTAL(109,tblFinancial384911[APR]) -> 0 | F83: =SUBTOTAL(109,tblFinancial384911[MAY]) -> 0 | G83: =SUBTOTAL(109,tblFinancial384911[JUN]) -> 0 | H83: =SUBTOTAL(109,tblFinancial384911[JUL]) -> 0 | I83: =SUBTOTAL(109,tblFinancial384911[AUG]) -> 0 | J83: =SUBTOTAL(109,tblFinancial384911[SEP]) -> 0 | K83: =SUBTOTAL(109,tblFinancial384911[OCT]) -> 0 | L83: =SUBTOTAL(109,tblFinancial384911[NOV]) -> 0 | M83: =SUBTOTAL(109,tblFinancial384911[DEC]) -> 0 | N83: =SUBTOTAL(109,tblFinancial384911[YEAR]) -> 1193
A85: MISC PAYMENTS | B85: JAN | C85: FEB | D85: MAR | E85: APR | F85: MAY | G85: JUN | H85: JUL | I85: AUG | J85: SEP | K85: OCT | L85: NOV | M85: DEC | N85: YEAR | O85: Last Updated on
A86: Other | N86: =SUM(tblMisc395012[[#This Row],[JAN]:[DEC]]) -> 0 | O86: 46058
A87: Total | B87: =SUBTOTAL(109,tblMisc395012[JAN]) -> 0 | C87: =SUBTOTAL(109,tblMisc395012[FEB]) -> 0 | D87: =SUBTOTAL(109,tblMisc395012[MAR]) -> 0 | E87: =SUBTOTAL(109,tblMisc395012[APR]) -> 0 | F87: =SUBTOTAL(109,tblMisc395012[MAY]) -> 0 | G87: =SUBTOTAL(109,tblMisc395012[JUN]) -> 0 | H87: =SUBTOTAL(109,tblMisc395012[JUL]) -> 0 | I87: =SUBTOTAL(109,tblMisc395012[AUG]) -> 0 | J87: =SUBTOTAL(109,tblMisc395012[SEP]) -> 0 | K87: =SUBTOTAL(109,tblMisc395012[OCT]) -> 0 | L87: =SUBTOTAL(109,tblMisc395012[NOV]) -> 0 | M87: =SUBTOTAL(109,tblMisc395012[DEC]) -> 0 | N87: =SUBTOTAL(109,tblMisc395012[YEAR]) -> 0
A89: Loan Payments | B89: Pending | C89: Total | D89: Cleared | E89: Interest | F89: EMI | I89: Pending | J89: Total
A90: Home Loan | B90: 19932.95 | C90: 22100.72 | D90: =C90-B90 -> 2167.77 | E90: 0.096 | F90: 23000 | I90: 21237.06 | J90: 21237.06
A91: Education Loan | B91: 9920.79 | C91: 9920.79 | D91: =C91-B91 -> 0 | E91: 0.0965 | F91: 12675 | I91: 9220.79 | J91: 9220.79
A92: Gold Loan | B92: 16184.06 | C92: 16184.06 | D92: =C92-B92 -> 0 | E92: 0.09 | I92: 16184.06 | J92: 16184.06
A93: Personal Loan | B93: 155 | C93: 11000 | D93: =C93-B93 -> 10845 | E93: 0.121 | F93: 0 | I93: 5065.96 | J93: 9943.62
A94: US Credit Cards | B94: =tblEntertainment32446[[#Totals],[Balance]] -> 7662 | C94: =tblEntertainment32446[[#Totals],[Balance]] -> 7662 | D94: =C94-B94 -> 0 | E94: 0 | I94: =tblEntertainment32446[[#Totals],[Balance]] -> 7662 | J94: =tblEntertainment32446[[#Totals],[Balance]] -> 7662
A95: Total | B95: =SUM(B90:B94) -> 53854.8 | C95: =SUM(C90:C94) -> 66867.57 | D95: =C95-B95 -> 13012.77 | I95: =SUM(I90:I94) -> 59369.87 | J95: =SUM(J90:J94) -> 64247.53
A97: TOTALS | B97: JAN | C97: FEB | D97: MAR | E97: APR | F97: MAY | G97: JUN | H97: JUL | I97: AUG | J97: SEP | K97: OCT | L97: NOV | M97: DEC | N97: YEAR
A98: Total expenses | B98: =SUM(B21,B28,B34,B43,B51,B69,B76,B83,B87) -> 3044.72 | C98: =SUM(C21,C28,C34,C43,C51,C69,C76,C83,C87) -> 321.99 | D98: =SUM(D21,D28,D34,D43,D51,D69,D76,D83,D87) -> 0 | E98: =SUM(E21,E28,E34,E43,E51,E69,E76,E83,E87) -> 0 | F98: =SUM(F21,F28,F34,F43,F51,F69,F76,F83,F87) -> 0 | G98: =SUM(G21,G28,G34,G43,G51,G69,G76,G83,G87) -> 0 | H98: =SUM(H21,H28,H34,H43,H51,H69,H76,H83,H87) -> 0 | I98: =SUM(I21,I28,I34,I43,I51,I69,I76,I83,I87) -> 0 | J98: =SUM(J21,J28,J34,J43,J51,J69,J76,J83,J87) -> 0 | K98: =SUM(K21,K28,K34,K43,K51,K69,K76,K83) -> 0 | L98: =SUM(L21,L28,L34,L43,L51,L69,L76,L83) -> 0 | M98: =SUM(M21,M28,M34,M43,M51,M69,M76,M83) -> 0 | N98: =SUM(N21,N28,N34,N43,N51,N69,N76,N83) -> 3366.71
A99: Monthly Expenses | B99: =SUM(tblHome29413[[#Totals],[JAN]] + tblDaily30424[[#Totals],[JAN]] + tblTransportation31435[[#Totals],[JAN]] + tblEntertainment32446[[#Totals],[JAN]] + tblVacations34457[[#Totals],[JAN]]+ tblDues36479[[#Totals],[JAN]]+ tblPersonal374810[[#Totals],[JAN]]) -> 2001.72 | C99: =SUM(tblHome29413[[#Totals],[FEB]] + tblDaily30424[[#Totals],[FEB]] + tblTransportation31435[[#Totals],[FEB]] + tblEntertainment32446[[#Totals],[FEB]] + tblVacations34457[[#Totals],[FEB]]+ tblDues36479[[#Totals],[FEB]]+ tblPersonal374810[[#Totals],[FEB]]) -> 171.99 | D99: =SUM(tblHome29413[[#Totals],[MAR]] + tblDaily30424[[#Totals],[MAR]] + tblTransportation31435[[#Totals],[MAR]] + tblEntertainment32446[[#Totals],[MAR]] + tblVacations34457[[#Totals],[MAR]]+ tblDues36479[[#Totals],[MAR]]+ tblPersonal374810[[#Totals],[MAR]]) -> 0 | E99: =SUM(tblHome29413[[#Totals],[APR]] + tblDaily30424[[#Totals],[APR]] + tblTransportation31435[[#Totals],[APR]] + tblEntertainment32446[[#Totals],[APR]] + tblVacations34457[[#Totals],[APR]]+ tblDues36479[[#Totals],[APR]]+ tblPersonal374810[[#Totals],[APR]]) -> 0 | F99: =SUM(tblHome29413[[#Totals],[MAY]] + tblDaily30424[[#Totals],[MAY]] + tblTransportation31435[[#Totals],[MAY]] + tblEntertainment32446[[#Totals],[MAY]] + tblVacations34457[[#Totals],[MAY]]+ tblDues36479[[#Totals],[MAY]]+ tblPersonal374810[[#Totals],[MAY]]) -> 0 | G99: =SUM(tblHome29413[[#Totals],[JUN]] + tblDaily30424[[#Totals],[JUN]] + tblTransportation31435[[#Totals],[JUN]] + tblEntertainment32446[[#Totals],[JUN]] + tblVacations34457[[#Totals],[JUN]]+ tblDues36479[[#Totals],[JUN]]+ tblPersonal374810[[#Totals],[JUN]]) -> 0 | H99: =SUM(tblHome29413[[#Totals],[JUL]] + tblDaily30424[[#Totals],[JUL]] + tblTransportation31435[[#Totals],[JUL]] + tblEntertainment32446[[#Totals],[JUL]] + tblVacations34457[[#Totals],[JUL]]+ tblDues36479[[#Totals],[JUL]]+ tblPersonal374810[[#Totals],[JUL]]) -> 0 | I99: =SUM(tblHome29413[[#Totals],[AUG]] + tblDaily30424[[#Totals],[AUG]] + tblTransportation31435[[#Totals],[AUG]] + tblEntertainment32446[[#Totals],[AUG]] + tblVacations34457[[#Totals],[AUG]]+ tblDues36479[[#Totals],[AUG]]+ tblPersonal374810[[#Totals],[AUG]]) -> 0 | J99: =SUM(tblHome29413[[#Totals],[SEP]] + tblDaily30424[[#Totals],[SEP]] + tblTransportation31435[[#Totals],[SEP]] + tblEntertainment32446[[#Totals],[SEP]] + tblVacations34457[[#Totals],[SEP]]+ tblDues36479[[#Totals],[SEP]]+ tblPersonal374810[[#Totals],[SEP]]) -> 0 | K99: =SUM(tblHome29413[[#Totals],[OCT]] + tblDaily30424[[#Totals],[OCT]] + tblTransportation31435[[#Totals],[OCT]] + tblEntertainment32446[[#Totals],[OCT]] + tblVacations34457[[#Totals],[OCT]]+ tblDues36479[[#Totals],[OCT]]+ tblPersonal374810[[#Totals],[OCT]]) -> 0 | L99: =SUM(tblHome29413[[#Totals],[NOV]] + tblDaily30424[[#Totals],[NOV]] + tblTransportation31435[[#Totals],[NOV]] + tblEntertainment32446[[#Totals],[NOV]] + tblVacations34457[[#Totals],[NOV]]+ tblDues36479[[#Totals],[NOV]]+ tblPersonal374810[[#Totals],[NOV]]) -> 0 | M99: =SUM(tblHome29413[[#Totals],[DEC]] + tblDaily30424[[#Totals],[DEC]] + tblTransportation31435[[#Totals],[DEC]] + tblEntertainment32446[[#Totals],[DEC]] + tblVacations34457[[#Totals],[DEC]]+ tblDues36479[[#Totals],[DEC]]+ tblPersonal374810[[#Totals],[DEC]]) -> 0 | N99: =SUM(tblHome29413[[#Totals],[YEAR]] + tblDaily30424[[#Totals],[YEAR]] + tblTransportation31435[[#Totals],[YEAR]] + tblEntertainment32446[[#Totals],[YEAR]] + tblVacations34457[[#Totals],[YEAR]]+ tblDues36479[[#Totals],[YEAR]]+ tblPersonal374810[[#Totals],[YEAR]]) -> 2173.71
A100: Invested | B100: =SUM(tblRecreation35468[[#Totals],[JAN]]) -> 0 | C100: =SUM(tblRecreation35468[[#Totals],[FEB]]) -> 0 | D100: =SUM(tblRecreation35468[[#Totals],[MAR]]) -> 0 | E100: =SUM(tblRecreation35468[[#Totals],[APR]]) -> 0 | F100: =SUM(tblRecreation35468[[#Totals],[MAY]]) -> 0 | G100: =SUM(tblRecreation35468[[#Totals],[JUN]]) -> 0 | H100: =SUM(tblRecreation35468[[#Totals],[JUL]]) -> 0 | I100: =SUM(tblRecreation35468[[#Totals],[AUG]]) -> 0 | J100: =SUM(tblRecreation35468[[#Totals],[SEP]]) -> 0 | K100: =SUM(tblRecreation35468[[#Totals],[OCT]]) -> 0 | L100: =SUM(tblRecreation35468[[#Totals],[NOV]]) -> 0 | M100: =SUM(tblRecreation35468[[#Totals],[DEC]]) -> 0 | N100: =SUM(I100:M100) -> 0
A103: Debt | B103: =I95 -> 59369.87
A104: Total Money sent
